{
   "geocoded_waypoints" : [
      {
         "geocoder_status" : "OK",
         "place_id" : "ChIJbfevC_6ZpgAR_R-g4-MuUFk",
         "types" : [ "street_address" ]
      },
      {
         "geocoder_status" : "OK",
         "place_id" : "ChIJMWh1Tl-XpgARaXDSSpbkVjg",
         "types" : [ "street_address" ]
      },
      {
         "geocoder_status" : "OK",
         "place_id" : "ChIJ01yj9F6XpgARJhcNGRerllc",
         "types" : [ "street_address" ]
      },
      {
         "geocoder_status" : "OK",
         "place_id" : "ChIJE_AciR2apgARPxS5vTrU42w",
         "types" : [ "street_address" ]
      },
      {
         "geocoder_status" : "OK",
         "place_id" : "EkdSdWEgR3VhaWN1cnVzLCAzNDgtMzU0IC0gQ2VudHJvLCBCZWxvIEhvcml6b250ZSAtIE1HLCAzMDExMS0wNjAsIEJyYXNpbA",
         "types" : [ "street_address" ]
      },
      {
         "geocoder_status" : "OK",
         "place_id" : "ChIJgQBmWfuZpgAR30cD4lINtkI",
         "types" : [ "establishment", "point_of_interest", "premise" ]
      },
      {
         "geocoder_status" : "OK",
         "place_id" : "EkdSdWEgR3VhaWN1cnVzLCAzNDgtMzU0IC0gQ2VudHJvLCBCZWxvIEhvcml6b250ZSAtIE1HLCAzMDExMS0wNjAsIEJyYXNpbA",
         "types" : [ "street_address" ]
      },
      {
         "geocoder_status" : "OK",
         "place_id" : "ChIJbfevC_6ZpgAR_R-g4-MuUFk",
         "types" : [ "street_address" ]
      }
   ],
   "routes" : [
      {
         "bounds" : {
            "northeast" : {
               "lat" : -19.9116376,
               "lng" : -43.9308349
            },
            "southwest" : {
               "lat" : -19.925697,
               "lng" : -43.9499661
            }
         },
         "copyrights" : "Map data ©2017 Google",
         "legs" : [
            {
               "distance" : {
                  "text" : "1.8 km",
                  "value" : 1836
               },
               "duration" : {
                  "text" : "9 mins",
                  "value" : 541
               },
               "end_address" : "Praça Raul Soares, 14 - Centro, Belo Horizonte - MG, 30180-030, Brazil",
               "end_location" : {
                  "lat" : -19.9231265,
                  "lng" : -43.9443893
               },
               "start_address" : "Av. do Contorno, 340 - Santa Efigênia, Belo Horizonte - MG, 30110-017, Brazil",
               "start_location" : {
                  "lat" : -19.9140985,
                  "lng" : -43.9417671
               },
               "steps" : [
                  {
                     "distance" : {
                        "text" : "0.1 km",
                        "value" : 107
                     },
                     "duration" : {
                        "text" : "1 min",
                        "value" : 38
                     },
                     "end_location" : {
                        "lat" : -19.9147983,
                        "lng" : -43.9420035
                     },
                     "html_instructions" : "Head \u003cb\u003esouthwest\u003c/b\u003e toward \u003cb\u003eR. Paulo de Frontin\u003c/b\u003e",
                     "polyline" : {
                        "points" : "bnpxB`kekGl@nA@??@@?@?B?B?BAp@_@DABAD?H@"
                     },
                     "start_location" : {
                        "lat" : -19.9140985,
                        "lng" : -43.9417671
                     },
                     "travel_mode" : "DRIVING"
                  },
                  {
                     "distance" : {
                        "text" : "0.2 km",
                        "value" : 235
                     },
                     "duration" : {
                        "text" : "1 min",
                        "value" : 69
                     },
                     "end_location" : {
                        "lat" : -19.916847,
                        "lng" : -43.9425552
                     },
                     "html_instructions" : "Continue onto \u003cb\u003eRua dos Guaranis\u003c/b\u003e",
                     "polyline" : {
                        "points" : "nrpxBnlekGpBVLBFBVHxFdA"
                     },
                     "start_location" : {
                        "lat" : -19.9147983,
                        "lng" : -43.9420035
                     },
                     "travel_mode" : "DRIVING"
                  },
                  {
                     "distance" : {
                        "text" : "0.2 km",
                        "value" : 180
                     },
                     "duration" : {
                        "text" : "1 min",
                        "value" : 70
                     },
                     "end_location" : {
                        "lat" : -19.9172426,
                        "lng" : -43.9408833
                     },
                     "html_instructions" : "Turn \u003cb\u003eleft\u003c/b\u003e onto \u003cb\u003eRua dos Tupinambás\u003c/b\u003e",
                     "maneuver" : "turn-left",
                     "polyline" : {
                        "points" : "h_qxB~oekG\\wCBM@MTmARmA"
                     },
                     "start_location" : {
                        "lat" : -19.916847,
                        "lng" : -43.9425552
                     },
                     "travel_mode" : "DRIVING"
                  },
                  {
                     "distance" : {
                        "text" : "1.0 km",
                        "value" : 972
                     },
                     "duration" : {
                        "text" : "4 mins",
                        "value" : 266
                     },
                     "end_location" : {
                        "lat" : -19.925697,
                        "lng" : -43.9431854
                     },
                     "html_instructions" : "Turn \u003cb\u003eright\u003c/b\u003e onto \u003cb\u003eR. Curitiba\u003c/b\u003e",
                     "maneuver" : "turn-right",
                     "polyline" : {
                        "points" : "vaqxBneekGl@JjEt@d@HlE|@RDjCb@~@Nb@FVF@Aj@Jh@Jj@J`@FXLTFNAJBD@B@bAPp@L^J`@HVBbBZz@L~@N~AXlB^VD"
                     },
                     "start_location" : {
                        "lat" : -19.9172426,
                        "lng" : -43.9408833
                     },
                     "travel_mode" : "DRIVING"
                  },
                  {
                     "distance" : {
                        "text" : "0.3 km",
                        "value" : 297
                     },
                     "duration" : {
                        "text" : "1 min",
                        "value" : 83
                     },
                     "end_location" : {
                        "lat" : -19.9234243,
                        "lng" : -43.9446739
                     },
                     "html_instructions" : "Turn \u003cb\u003eright\u003c/b\u003e onto \u003cb\u003eAv. Bias Fortes\u003c/b\u003e",
                     "maneuver" : "turn-right",
                     "polyline" : {
                        "points" : "rvrxB|sekGaCrA{Az@WNQLOHg@RgCzA"
                     },
                     "start_location" : {
                        "lat" : -19.925697,
                        "lng" : -43.9431854
                     },
                     "travel_mode" : "DRIVING"
                  },
                  {
                     "distance" : {
                        "text" : "45 m",
                        "value" : 45
                     },
                     "duration" : {
                        "text" : "1 min",
                        "value" : 15
                     },
                     "end_location" : {
                        "lat" : -19.9231265,
                        "lng" : -43.9443893
                     },
                     "html_instructions" : "Turn \u003cb\u003eright\u003c/b\u003e onto \u003cb\u003ePraça Raul Soares\u003c/b\u003e\u003cdiv style=\"font-size:0.9em\"\u003eDestination will be on the right\u003c/div\u003e",
                     "maneuver" : "turn-right",
                     "polyline" : {
                        "points" : "jhrxBd}ekGEEGKIIGGKIIGCA"
                     },
                     "start_location" : {
                        "lat" : -19.9234243,
                        "lng" : -43.9446739
                     },
                     "travel_mode" : "DRIVING"
                  }
               ],
               "traffic_speed_entry" : [],
               "via_waypoint" : []
            },
            {
               "distance" : {
                  "text" : "1.3 km",
                  "value" : 1263
               },
               "duration" : {
                  "text" : "5 mins",
                  "value" : 321
               },
               "end_address" : "Av. Amazonas, 1445 - Centro, Belo Horizonte - MG, Brazil",
               "end_location" : {
                  "lat" : -19.9240215,
                  "lng" : -43.9472569
               },
               "start_address" : "Praça Raul Soares, 14 - Centro, Belo Horizonte - MG, 30180-030, Brazil",
               "start_location" : {
                  "lat" : -19.9231265,
                  "lng" : -43.9443893
               },
               "steps" : [
                  {
                     "distance" : {
                        "text" : "0.4 km",
                        "value" : 373
                     },
                     "duration" : {
                        "text" : "2 mins",
                        "value" : 110
                     },
                     "end_location" : {
                        "lat" : -19.9231144,
                        "lng" : -43.9459322
                     },
                     "html_instructions" : "Head \u003cb\u003enortheast\u003c/b\u003e on \u003cb\u003ePraça Raul Soares\u003c/b\u003e toward \u003cb\u003eAv. Augusto de Lima\u003c/b\u003e",
                     "polyline" : {
                        "points" : "pfrxBl{ekGGCKESGKAKAMAK?M@K@KBKD]PGFGFGHEHEHEHIPENCPCPAN?N?NBNBLDJDLHNDFFJHJFHHFRJPDRDJ?L?J?LALALCJEJE"
                     },
                     "start_location" : {
                        "lat" : -19.9231265,
                        "lng" : -43.9443893
                     },
                     "travel_mode" : "DRIVING"
                  },
                  {
                     "distance" : {
                        "text" : "0.1 km",
                        "value" : 113
                     },
                     "duration" : {
                        "text" : "1 min",
                        "value" : 30
                     },
                     "end_location" : {
                        "lat" : -19.9236342,
                        "lng" : -43.9468597
                     },
                     "html_instructions" : "Turn \u003cb\u003eright\u003c/b\u003e onto \u003cb\u003eAv. Amazonas\u003c/b\u003e (signs for \u003cb\u003ePrado\u003c/b\u003e/\u003cb\u003eExpominas\u003c/b\u003e/\u003cb\u003eBetim\u003c/b\u003e/\u003cb\u003eSão Paulo\u003c/b\u003e)",
                     "maneuver" : "turn-right",
                     "polyline" : {
                        "points" : "lfrxB`efkGj@lATf@Td@FNFL"
                     },
                     "start_location" : {
                        "lat" : -19.9231144,
                        "lng" : -43.9459322
                     },
                     "travel_mode" : "DRIVING"
                  },
                  {
                     "distance" : {
                        "text" : "0.4 km",
                        "value" : 377
                     },
                     "duration" : {
                        "text" : "1 min",
                        "value" : 57
                     },
                     "end_location" : {
                        "lat" : -19.9253462,
                        "lng" : -43.9499661
                     },
                     "html_instructions" : "Continue straight to stay on \u003cb\u003eAv. Amazonas\u003c/b\u003e",
                     "maneuver" : "straight",
                     "polyline" : {
                        "points" : "tirxBzjfkGtAxCTh@d@dAPXLVFNlAnCnApC"
                     },
                     "start_location" : {
                        "lat" : -19.9236342,
                        "lng" : -43.9468597
                     },
                     "travel_mode" : "DRIVING"
                  },
                  {
                     "distance" : {
                        "text" : "0.1 km",
                        "value" : 124
                     },
                     "duration" : {
                        "text" : "1 min",
                        "value" : 33
                     },
                     "end_location" : {
                        "lat" : -19.9242715,
                        "lng" : -43.9496669
                     },
                     "html_instructions" : "Turn \u003cb\u003eright\u003c/b\u003e onto \u003cb\u003eR. Araguari\u003c/b\u003e",
                     "maneuver" : "turn-right",
                     "polyline" : {
                        "points" : "ltrxBh~fkGkB]kB]"
                     },
                     "start_location" : {
                        "lat" : -19.9253462,
                        "lng" : -43.9499661
                     },
                     "travel_mode" : "DRIVING"
                  },
                  {
                     "distance" : {
                        "text" : "0.1 km",
                        "value" : 125
                     },
                     "duration" : {
                        "text" : "1 min",
                        "value" : 50
                     },
                     "end_location" : {
                        "lat" : -19.9245567,
                        "lng" : -43.948515
                     },
                     "html_instructions" : "Turn \u003cb\u003eright\u003c/b\u003e at the 1st cross street onto \u003cb\u003eRua dos Timbiras\u003c/b\u003e",
                     "maneuver" : "turn-right",
                     "polyline" : {
                        "points" : "tmrxBl|fkGRkAd@yC"
                     },
                     "start_location" : {
                        "lat" : -19.9242715,
                        "lng" : -43.9496669
                     },
                     "travel_mode" : "DRIVING"
                  },
                  {
                     "distance" : {
                        "text" : "0.2 km",
                        "value" : 151
                     },
                     "duration" : {
                        "text" : "1 min",
                        "value" : 41
                     },
                     "end_location" : {
                        "lat" : -19.9240215,
                        "lng" : -43.9472569
                     },
                     "html_instructions" : "Turn \u003cb\u003eleft\u003c/b\u003e onto \u003cb\u003eAv. Amazonas\u003c/b\u003e\u003cdiv style=\"font-size:0.9em\"\u003eDestination will be on the right\u003c/div\u003e",
                     "maneuver" : "turn-left",
                     "polyline" : {
                        "points" : "norxBfufkGBYDUcBkDQ_@"
                     },
                     "start_location" : {
                        "lat" : -19.9245567,
                        "lng" : -43.948515
                     },
                     "travel_mode" : "DRIVING"
                  }
               ],
               "traffic_speed_entry" : [],
               "via_waypoint" : []
            },
            {
               "distance" : {
                  "text" : "3.1 km",
                  "value" : 3099
               },
               "duration" : {
                  "text" : "8 mins",
                  "value" : 495
               },
               "end_address" : "R. Célio de Castro, 869 - Floresta, Belo Horizonte - MG, Brazil",
               "end_location" : {
                  "lat" : -19.9127637,
                  "lng" : -43.9310629
               },
               "start_address" : "Av. Amazonas, 1445 - Centro, Belo Horizonte - MG, Brazil",
               "start_location" : {
                  "lat" : -19.9240215,
                  "lng" : -43.9472569
               },
               "steps" : [
                  {
                     "distance" : {
                        "text" : "0.2 km",
                        "value" : 171
                     },
                     "duration" : {
                        "text" : "1 min",
                        "value" : 39
                     },
                     "end_location" : {
                        "lat" : -19.9232325,
                        "lng" : -43.9458575
                     },
                     "html_instructions" : "Head \u003cb\u003enortheast\u003c/b\u003e on \u003cb\u003eAv. Amazonas\u003c/b\u003e toward \u003cb\u003eRua dos Guajajaras\u003c/b\u003e/\u003cb\u003eR. Rio Grande do Sul\u003c/b\u003e",
                     "polyline" : {
                        "points" : "blrxBjmfkGKUi@iAQ[k@mAi@mA"
                     },
                     "start_location" : {
                        "lat" : -19.9240215,
                        "lng" : -43.9472569
                     },
                     "travel_mode" : "DRIVING"
                  },
                  {
                     "distance" : {
                        "text" : "0.4 km",
                        "value" : 407
                     },
                     "duration" : {
                        "text" : "2 mins",
                        "value" : 127
                     },
                     "end_location" : {
                        "lat" : -19.9220051,
                        "lng" : -43.9455106
                     },
                     "html_instructions" : "Turn \u003cb\u003eright\u003c/b\u003e onto \u003cb\u003ePraça Raul Soares\u003c/b\u003e (signs for \u003cb\u003eMinascentro\u003c/b\u003e)",
                     "maneuver" : "turn-right",
                     "polyline" : {
                        "points" : "dgrxBrdfkGHIFGFIFIDIDKDKBKDQ@M?M@MAMAMAMCMCIGQEIEEGKIIGGKIIGKEKESGKAKAMAK?M@K@KBKD]PGFGFGHEHEHEHIPENCPCPAN?N?NBNBLDJ"
                     },
                     "start_location" : {
                        "lat" : -19.9232325,
                        "lng" : -43.9458575
                     },
                     "travel_mode" : "DRIVING"
                  },
                  {
                     "distance" : {
                        "text" : "0.3 km",
                        "value" : 311
                     },
                     "duration" : {
                        "text" : "1 min",
                        "value" : 60
                     },
                     "end_location" : {
                        "lat" : -19.9196065,
                        "lng" : -43.9470446
                     },
                     "html_instructions" : "Turn \u003cb\u003eright\u003c/b\u003e onto \u003cb\u003eAv. Bias Fortes\u003c/b\u003e",
                     "maneuver" : "turn-right",
                     "polyline" : {
                        "points" : "p_rxBlbfkGgAl@iAl@_Af@cBz@QHcBbAa@VIDGD"
                     },
                     "start_location" : {
                        "lat" : -19.9220051,
                        "lng" : -43.9455106
                     },
                     "travel_mode" : "DRIVING"
                  },
                  {
                     "distance" : {
                        "text" : "0.2 km",
                        "value" : 218
                     },
                     "duration" : {
                        "text" : "1 min",
                        "value" : 48
                     },
                     "end_location" : {
                        "lat" : -19.9177246,
                        "lng" : -43.9464643
                     },
                     "html_instructions" : "Turn \u003cb\u003eright\u003c/b\u003e onto \u003cb\u003eR. Mato Grosso\u003c/b\u003e",
                     "maneuver" : "turn-right",
                     "polyline" : {
                        "points" : "ppqxB~kfkGWGeAUeCi@iAUkAU"
                     },
                     "start_location" : {
                        "lat" : -19.9196065,
                        "lng" : -43.9470446
                     },
                     "travel_mode" : "DRIVING"
                  },
                  {
                     "distance" : {
                        "text" : "65 m",
                        "value" : 65
                     },
                     "duration" : {
                        "text" : "1 min",
                        "value" : 13
                     },
                     "end_location" : {
                        "lat" : -19.9171491,
                        "lng" : -43.9463803
                     },
                     "html_instructions" : "Take the ramp on the \u003cb\u003eleft\u003c/b\u003e to \u003cb\u003eAv. Anto Carlos\u003c/b\u003e/\u003cb\u003eAv. Crist. Machado\u003c/b\u003e/\u003cb\u003eVitória\u003c/b\u003e",
                     "polyline" : {
                        "points" : "vdqxBjhfkG{@KOAS?QA"
                     },
                     "start_location" : {
                        "lat" : -19.9177246,
                        "lng" : -43.9464643
                     },
                     "travel_mode" : "DRIVING"
                  },
                  {
                     "distance" : {
                        "text" : "0.6 km",
                        "value" : 633
                     },
                     "duration" : {
                        "text" : "1 min",
                        "value" : 47
                     },
                     "end_location" : {
                        "lat" : -19.912904,
                        "lng" : -43.9429084
                     },
                     "html_instructions" : "Merge onto \u003cb\u003eAv. Nossa Sra. de Fátima\u003c/b\u003e",
                     "maneuver" : "merge",
                     "polyline" : {
                        "points" : "daqxBzgfkGu@q@{BkBuAiAc@c@IEYYSMSKSGQEQCUCM?a@@]@S@W?]CSGWIOIMMKIEIGQOi@Um@aAwBg@{@"
                     },
                     "start_location" : {
                        "lat" : -19.9171491,
                        "lng" : -43.9463803
                     },
                     "travel_mode" : "DRIVING"
                  },
                  {
                     "distance" : {
                        "text" : "0.2 km",
                        "value" : 229
                     },
                     "duration" : {
                        "text" : "1 min",
                        "value" : 15
                     },
                     "end_location" : {
                        "lat" : -19.9118702,
                        "lng" : -43.941037
                     },
                     "html_instructions" : "Take the ramp to \u003cb\u003eAv. Antº Carlos\u003c/b\u003e/\u003cb\u003ePampulha\u003c/b\u003e",
                     "polyline" : {
                        "points" : "rfpxBdrekGCUy@iBm@oAYo@Yo@Wq@CGCCGEEA"
                     },
                     "start_location" : {
                        "lat" : -19.912904,
                        "lng" : -43.9429084
                     },
                     "travel_mode" : "DRIVING"
                  },
                  {
                     "distance" : {
                        "text" : "0.1 km",
                        "value" : 112
                     },
                     "duration" : {
                        "text" : "1 min",
                        "value" : 8
                     },
                     "end_location" : {
                        "lat" : -19.9116376,
                        "lng" : -43.9399953
                     },
                     "html_instructions" : "Continue onto \u003cb\u003eAv. Pres. Antônio Carlos\u003c/b\u003e",
                     "polyline" : {
                        "points" : "d`pxBnfekGOw@Ge@Iy@Kw@"
                     },
                     "start_location" : {
                        "lat" : -19.9118702,
                        "lng" : -43.941037
                     },
                     "travel_mode" : "DRIVING"
                  },
                  {
                     "distance" : {
                        "text" : "1.0 km",
                        "value" : 953
                     },
                     "duration" : {
                        "text" : "2 mins",
                        "value" : 138
                     },
                     "end_location" : {
                        "lat" : -19.9127637,
                        "lng" : -43.9310629
                     },
                     "html_instructions" : "Slight \u003cb\u003eright\u003c/b\u003e onto \u003cb\u003eR. Célio de Castro\u003c/b\u003e\u003cdiv style=\"font-size:0.9em\"\u003eDestination will be on the right\u003c/div\u003e",
                     "maneuver" : "turn-slight-right",
                     "polyline" : {
                        "points" : "v~oxB~_ekGJcAH[BU@Q@KBE@K@C~@{F`@eCFc@DU@K?M?o@?k@?cA?oBGsG?w@?qA?sA@y@@Y@ODWDUD_@Fc@LeAFk@BO@GBE@CBCBEBC@A"
                     },
                     "start_location" : {
                        "lat" : -19.9116376,
                        "lng" : -43.9399953
                     },
                     "travel_mode" : "DRIVING"
                  }
               ],
               "traffic_speed_entry" : [],
               "via_waypoint" : []
            },
            {
               "distance" : {
                  "text" : "0.8 km",
                  "value" : 817
               },
               "duration" : {
                  "text" : "3 mins",
                  "value" : 195
               },
               "end_address" : "Rua Guaicurus, 348-354 - Centro, Belo Horizonte - MG, 30111-060, Brazil",
               "end_location" : {
                  "lat" : -19.9152414,
                  "lng" : -43.9368628
               },
               "start_address" : "R. Célio de Castro, 869 - Floresta, Belo Horizonte - MG, Brazil",
               "start_location" : {
                  "lat" : -19.9127637,
                  "lng" : -43.9310629
               },
               "steps" : [
                  {
                     "distance" : {
                        "text" : "49 m",
                        "value" : 49
                     },
                     "duration" : {
                        "text" : "1 min",
                        "value" : 9
                     },
                     "end_location" : {
                        "lat" : -19.9131516,
                        "lng" : -43.9308349
                     },
                     "html_instructions" : "Head \u003cb\u003esoutheast\u003c/b\u003e on \u003cb\u003eR. Célio de Castro\u003c/b\u003e toward \u003cb\u003eAv. do Contorno\u003c/b\u003e",
                     "polyline" : {
                        "points" : "vepxBbhckGBALIRKLGHENG"
                     },
                     "start_location" : {
                        "lat" : -19.9127637,
                        "lng" : -43.9310629
                     },
                     "travel_mode" : "DRIVING"
                  },
                  {
                     "distance" : {
                        "text" : "0.1 km",
                        "value" : 101
                     },
                     "duration" : {
                        "text" : "1 min",
                        "value" : 28
                     },
                     "end_location" : {
                        "lat" : -19.9135807,
                        "lng" : -43.9316901
                     },
                     "html_instructions" : "Turn \u003cb\u003eright\u003c/b\u003e onto \u003cb\u003eAv. do Contorno\u003c/b\u003e",
                     "maneuver" : "turn-right",
                     "polyline" : {
                        "points" : "dhpxBtfckGb@bA^bAPb@"
                     },
                     "start_location" : {
                        "lat" : -19.9131516,
                        "lng" : -43.9308349
                     },
                     "travel_mode" : "DRIVING"
                  },
                  {
                     "distance" : {
                        "text" : "0.3 km",
                        "value" : 288
                     },
                     "duration" : {
                        "text" : "1 min",
                        "value" : 58
                     },
                     "end_location" : {
                        "lat" : -19.9149596,
                        "lng" : -43.9340008
                     },
                     "html_instructions" : "Slight \u003cb\u003eleft\u003c/b\u003e to stay on \u003cb\u003eAv. do Contorno\u003c/b\u003e",
                     "maneuver" : "turn-slight-left",
                     "polyline" : {
                        "points" : "zjpxB`lckG\\Rj@pAXj@^p@^p@FP^|@h@lAL\\NZ"
                     },
                     "start_location" : {
                        "lat" : -19.9135807,
                        "lng" : -43.9316901
                     },
                     "travel_mode" : "DRIVING"
                  },
                  {
                     "distance" : {
                        "text" : "93 m",
                        "value" : 93
                     },
                     "duration" : {
                        "text" : "1 min",
                        "value" : 23
                     },
                     "end_location" : {
                        "lat" : -19.9157357,
                        "lng" : -43.934236
                     },
                     "html_instructions" : "\u003cb\u003eAv. do Contorno\u003c/b\u003e turns \u003cb\u003eleft\u003c/b\u003e and becomes \u003cb\u003eAv. dos Andradas\u003c/b\u003e",
                     "polyline" : {
                        "points" : "nspxBnzckGPLJJPCD?h@Hz@N"
                     },
                     "start_location" : {
                        "lat" : -19.9149596,
                        "lng" : -43.9340008
                     },
                     "travel_mode" : "DRIVING"
                  },
                  {
                     "distance" : {
                        "text" : "77 m",
                        "value" : 77
                     },
                     "duration" : {
                        "text" : "1 min",
                        "value" : 16
                     },
                     "end_location" : {
                        "lat" : -19.9157232,
                        "lng" : -43.9349297
                     },
                     "html_instructions" : "Turn \u003cb\u003eright\u003c/b\u003e onto \u003cb\u003eRua Guaicurus\u003c/b\u003e (signs for \u003cb\u003eAv. Pedro II\u003c/b\u003e/\u003cb\u003eAv. Amazonas\u003c/b\u003e/\u003cb\u003ePraça Sete\u003c/b\u003e)",
                     "maneuver" : "turn-right",
                     "polyline" : {
                        "points" : "jxpxB~{ckGFRJRCRSlA"
                     },
                     "start_location" : {
                        "lat" : -19.9157357,
                        "lng" : -43.934236
                     },
                     "travel_mode" : "DRIVING"
                  },
                  {
                     "distance" : {
                        "text" : "0.2 km",
                        "value" : 209
                     },
                     "duration" : {
                        "text" : "1 min",
                        "value" : 61
                     },
                     "end_location" : {
                        "lat" : -19.9152414,
                        "lng" : -43.9368628
                     },
                     "html_instructions" : "Continue straight to stay on \u003cb\u003eRua Guaicurus\u003c/b\u003e\u003cdiv style=\"font-size:0.9em\"\u003eDestination will be on the left\u003c/div\u003e",
                     "maneuver" : "straight",
                     "polyline" : {
                        "points" : "fxpxBh`dkG_AdG_@zB"
                     },
                     "start_location" : {
                        "lat" : -19.9157232,
                        "lng" : -43.9349297
                     },
                     "travel_mode" : "DRIVING"
                  }
               ],
               "traffic_speed_entry" : [],
               "via_waypoint" : []
            },
            {
               "distance" : {
                  "text" : "0.7 km",
                  "value" : 748
               },
               "duration" : {
                  "text" : "4 mins",
                  "value" : 240
               },
               "end_address" : "Obelisco Praça Sete - Av. Afonso Pena - Centro, Belo Horizonte - MG, 31840-190, Brazil",
               "end_location" : {
                  "lat" : -19.9191852,
                  "lng" : -43.9387306
               },
               "start_address" : "Rua Guaicurus, 348-354 - Centro, Belo Horizonte - MG, 30111-060, Brazil",
               "start_location" : {
                  "lat" : -19.9152414,
                  "lng" : -43.9368628
               },
               "steps" : [
                  {
                     "distance" : {
                        "text" : "0.2 km",
                        "value" : 212
                     },
                     "duration" : {
                        "text" : "1 min",
                        "value" : 65
                     },
                     "end_location" : {
                        "lat" : -19.9147549,
                        "lng" : -43.9388253
                     },
                     "html_instructions" : "Head \u003cb\u003ewest\u003c/b\u003e on \u003cb\u003eRua Guaicurus\u003c/b\u003e toward \u003cb\u003eR. Rio de Janeiro\u003c/b\u003e",
                     "polyline" : {
                        "points" : "fupxBjldkGAD_@`C_@~B_@`C"
                     },
                     "start_location" : {
                        "lat" : -19.9152414,
                        "lng" : -43.9368628
                     },
                     "travel_mode" : "DRIVING"
                  },
                  {
                     "distance" : {
                        "text" : "0.3 km",
                        "value" : 308
                     },
                     "duration" : {
                        "text" : "2 mins",
                        "value" : 113
                     },
                     "end_location" : {
                        "lat" : -19.9174328,
                        "lng" : -43.9395599
                     },
                     "html_instructions" : "Turn \u003cb\u003eleft\u003c/b\u003e onto \u003cb\u003eR. São Paulo\u003c/b\u003e",
                     "maneuver" : "turn-left",
                     "polyline" : {
                        "points" : "drpxBtxdkGhAPhAPJBJBfARhARPDr@LpATJBt@N"
                     },
                     "start_location" : {
                        "lat" : -19.9147549,
                        "lng" : -43.9388253
                     },
                     "travel_mode" : "DRIVING"
                  },
                  {
                     "distance" : {
                        "text" : "0.2 km",
                        "value" : 228
                     },
                     "duration" : {
                        "text" : "1 min",
                        "value" : 62
                     },
                     "end_location" : {
                        "lat" : -19.9191852,
                        "lng" : -43.9387306
                     },
                     "html_instructions" : "Continue straight onto \u003cb\u003eAv. Afonso Pena\u003c/b\u003e\u003cdiv style=\"font-size:0.9em\"\u003eDestination will be on the left\u003c/div\u003e",
                     "maneuver" : "straight",
                     "polyline" : {
                        "points" : "|bqxBf}dkGTZFELIv@_@`Am@dCcA\\QTM"
                     },
                     "start_location" : {
                        "lat" : -19.9174328,
                        "lng" : -43.9395599
                     },
                     "travel_mode" : "DRIVING"
                  }
               ],
               "traffic_speed_entry" : [],
               "via_waypoint" : []
            },
            {
               "distance" : {
                  "text" : "1.3 km",
                  "value" : 1307
               },
               "duration" : {
                  "text" : "5 mins",
                  "value" : 305
               },
               "end_address" : "Rua Guaicurus, 348-354 - Centro, Belo Horizonte - MG, 30111-060, Brazil",
               "end_location" : {
                  "lat" : -19.9152414,
                  "lng" : -43.9368628
               },
               "start_address" : "Obelisco Praça Sete - Av. Afonso Pena - Centro, Belo Horizonte - MG, 31840-190, Brazil",
               "start_location" : {
                  "lat" : -19.9191852,
                  "lng" : -43.9387306
               },
               "steps" : [
                  {
                     "distance" : {
                        "text" : "0.2 km",
                        "value" : 212
                     },
                     "duration" : {
                        "text" : "1 min",
                        "value" : 36
                     },
                     "end_location" : {
                        "lat" : -19.920802,
                        "lng" : -43.937665
                     },
                     "html_instructions" : "Head \u003cb\u003esoutheast\u003c/b\u003e on \u003cb\u003eAv. Afonso Pena\u003c/b\u003e toward \u003cb\u003eAv. Amazonas\u003c/b\u003e",
                     "polyline" : {
                        "points" : "|mqxB`xdkGPKPMtDuBfAm@^W"
                     },
                     "start_location" : {
                        "lat" : -19.9191852,
                        "lng" : -43.9387306
                     },
                     "travel_mode" : "DRIVING"
                  },
                  {
                     "distance" : {
                        "text" : "0.1 km",
                        "value" : 124
                     },
                     "duration" : {
                        "text" : "1 min",
                        "value" : 32
                     },
                     "end_location" : {
                        "lat" : -19.9218666,
                        "lng" : -43.9380169
                     },
                     "html_instructions" : "Turn \u003cb\u003eright\u003c/b\u003e onto \u003cb\u003eR. Espírito Santo\u003c/b\u003e (signs for \u003cb\u003eViad. Santa Tereza\u003c/b\u003e/\u003cb\u003eAeroporto Internacional\u003c/b\u003e)",
                     "maneuver" : "turn-right",
                     "polyline" : {
                        "points" : "~wqxBjqdkGv@RfB`@FDRBXF"
                     },
                     "start_location" : {
                        "lat" : -19.920802,
                        "lng" : -43.937665
                     },
                     "travel_mode" : "DRIVING"
                  },
                  {
                     "distance" : {
                        "text" : "0.1 km",
                        "value" : 119
                     },
                     "duration" : {
                        "text" : "1 min",
                        "value" : 34
                     },
                     "end_location" : {
                        "lat" : -19.9220184,
                        "lng" : -43.9369264
                     },
                     "html_instructions" : "Turn \u003cb\u003eleft\u003c/b\u003e at the 1st cross street onto \u003cb\u003eRua dos Tupis\u003c/b\u003e",
                     "maneuver" : "turn-left",
                     "polyline" : {
                        "points" : "t~qxBrsdkGh@eEACACCECE"
                     },
                     "start_location" : {
                        "lat" : -19.9218666,
                        "lng" : -43.9380169
                     },
                     "travel_mode" : "DRIVING"
                  },
                  {
                     "distance" : {
                        "text" : "0.2 km",
                        "value" : 193
                     },
                     "duration" : {
                        "text" : "1 min",
                        "value" : 34
                     },
                     "end_location" : {
                        "lat" : -19.9205475,
                        "lng" : -43.9376498
                     },
                     "html_instructions" : "Turn \u003cb\u003eleft\u003c/b\u003e at the 1st cross street onto \u003cb\u003eAv. Afonso Pena\u003c/b\u003e",
                     "maneuver" : "turn-left",
                     "polyline" : {
                        "points" : "r_rxBxldkGYYOJYHaAh@{@d@a@Xe@X[N"
                     },
                     "start_location" : {
                        "lat" : -19.9220184,
                        "lng" : -43.9369264
                     },
                     "travel_mode" : "DRIVING"
                  },
                  {
                     "distance" : {
                        "text" : "0.6 km",
                        "value" : 591
                     },
                     "duration" : {
                        "text" : "2 mins",
                        "value" : 148
                     },
                     "end_location" : {
                        "lat" : -19.9154002,
                        "lng" : -43.9362362
                     },
                     "html_instructions" : "Turn \u003cb\u003eright\u003c/b\u003e onto \u003cb\u003eR. Espírito Santo\u003c/b\u003e (signs for \u003cb\u003eAv. Crist. Machado\u003c/b\u003e/\u003cb\u003ePampulha\u003c/b\u003e/\u003cb\u003eAerop. Internacional\u003c/b\u003e/\u003cb\u003eVitória\u003c/b\u003e)",
                     "maneuver" : "turn-right",
                     "polyline" : {
                        "points" : "lvqxBhqdkGa@GiCg@o@KiCe@_B[WCs@Ou@McCc@mAUcASIAGAkASiAS"
                     },
                     "start_location" : {
                        "lat" : -19.9205475,
                        "lng" : -43.9376498
                     },
                     "travel_mode" : "DRIVING"
                  },
                  {
                     "distance" : {
                        "text" : "68 m",
                        "value" : 68
                     },
                     "duration" : {
                        "text" : "1 min",
                        "value" : 21
                     },
                     "end_location" : {
                        "lat" : -19.9152414,
                        "lng" : -43.9368628
                     },
                     "html_instructions" : "Turn \u003cb\u003eleft\u003c/b\u003e onto \u003cb\u003eRua Guaicurus\u003c/b\u003e\u003cdiv style=\"font-size:0.9em\"\u003eDestination will be on the left\u003c/div\u003e",
                     "maneuver" : "turn-left",
                     "polyline" : {
                        "points" : "fvpxBnhdkG_@zB"
                     },
                     "start_location" : {
                        "lat" : -19.9154002,
                        "lng" : -43.9362362
                     },
                     "travel_mode" : "DRIVING"
                  }
               ],
               "traffic_speed_entry" : [],
               "via_waypoint" : []
            },
            {
               "distance" : {
                  "text" : "1.0 km",
                  "value" : 1033
               },
               "duration" : {
                  "text" : "6 mins",
                  "value" : 337
               },
               "end_address" : "Av. do Contorno, 340 - Santa Efigênia, Belo Horizonte - MG, 30110-017, Brazil",
               "end_location" : {
                  "lat" : -19.9140985,
                  "lng" : -43.9417671
               },
               "start_address" : "Rua Guaicurus, 348-354 - Centro, Belo Horizonte - MG, 30111-060, Brazil",
               "start_location" : {
                  "lat" : -19.9152414,
                  "lng" : -43.9368628
               },
               "steps" : [
                  {
                     "distance" : {
                        "text" : "0.2 km",
                        "value" : 212
                     },
                     "duration" : {
                        "text" : "1 min",
                        "value" : 65
                     },
                     "end_location" : {
                        "lat" : -19.9147549,
                        "lng" : -43.9388253
                     },
                     "html_instructions" : "Head \u003cb\u003ewest\u003c/b\u003e on \u003cb\u003eRua Guaicurus\u003c/b\u003e toward \u003cb\u003eR. Rio de Janeiro\u003c/b\u003e",
                     "polyline" : {
                        "points" : "fupxBjldkGAD_@`C_@~B_@`C"
                     },
                     "start_location" : {
                        "lat" : -19.9152414,
                        "lng" : -43.9368628
                     },
                     "travel_mode" : "DRIVING"
                  },
                  {
                     "distance" : {
                        "text" : "0.3 km",
                        "value" : 276
                     },
                     "duration" : {
                        "text" : "2 mins",
                        "value" : 97
                     },
                     "end_location" : {
                        "lat" : -19.9171591,
                        "lng" : -43.9394812
                     },
                     "html_instructions" : "Turn \u003cb\u003eleft\u003c/b\u003e onto \u003cb\u003eR. São Paulo\u003c/b\u003e",
                     "maneuver" : "turn-left",
                     "polyline" : {
                        "points" : "drpxBtxdkGhAPhAPJBJBfARhARPDr@LpATJB"
                     },
                     "start_location" : {
                        "lat" : -19.9147549,
                        "lng" : -43.9388253
                     },
                     "travel_mode" : "DRIVING"
                  },
                  {
                     "distance" : {
                        "text" : "0.2 km",
                        "value" : 174
                     },
                     "duration" : {
                        "text" : "1 min",
                        "value" : 51
                     },
                     "end_location" : {
                        "lat" : -19.9160326,
                        "lng" : -43.9404529
                     },
                     "html_instructions" : "Turn \u003cb\u003eright\u003c/b\u003e onto \u003cb\u003eAv. Afonso Pena\u003c/b\u003e",
                     "maneuver" : "turn-right",
                     "polyline" : {
                        "points" : "faqxBv|dkGBJ@D@DADAHCHCD]RgCnAw@d@"
                     },
                     "start_location" : {
                        "lat" : -19.9171591,
                        "lng" : -43.9394812
                     },
                     "travel_mode" : "DRIVING"
                  },
                  {
                     "distance" : {
                        "text" : "89 m",
                        "value" : 89
                     },
                     "duration" : {
                        "text" : "1 min",
                        "value" : 20
                     },
                     "end_location" : {
                        "lat" : -19.9152571,
                        "lng" : -43.9403703
                     },
                     "html_instructions" : "\u003cb\u003eAv. Afonso Pena\u003c/b\u003e turns slightly \u003cb\u003eright\u003c/b\u003e and becomes \u003cb\u003ePraça Rio Branco\u003c/b\u003e/\u003cb\u003eR. Curitiba\u003c/b\u003e",
                     "polyline" : {
                        "points" : "dzpxBxbekGMDG@E@C?E?SCWEgAO"
                     },
                     "start_location" : {
                        "lat" : -19.9160326,
                        "lng" : -43.9404529
                     },
                     "travel_mode" : "DRIVING"
                  },
                  {
                     "distance" : {
                        "text" : "64 m",
                        "value" : 64
                     },
                     "duration" : {
                        "text" : "1 min",
                        "value" : 18
                     },
                     "end_location" : {
                        "lat" : -19.9150547,
                        "lng" : -43.9408238
                     },
                     "html_instructions" : "Turn \u003cb\u003eleft\u003c/b\u003e onto \u003cb\u003eCorredor MOVE Centro\u003c/b\u003e/\u003cb\u003ePraça Rio Branco\u003c/b\u003e",
                     "maneuver" : "turn-left",
                     "polyline" : {
                        "points" : "jupxBhbekGKAMAGn@Gl@"
                     },
                     "start_location" : {
                        "lat" : -19.9152571,
                        "lng" : -43.9403703
                     },
                     "travel_mode" : "DRIVING"
                  },
                  {
                     "distance" : {
                        "text" : "0.1 km",
                        "value" : 96
                     },
                     "duration" : {
                        "text" : "1 min",
                        "value" : 40
                     },
                     "end_location" : {
                        "lat" : -19.9143135,
                        "lng" : -43.9409559
                     },
                     "html_instructions" : "\u003cb\u003eCorredor MOVE Centro\u003c/b\u003e/\u003cb\u003ePraça Rio Branco\u003c/b\u003e turns slightly \u003cb\u003eright\u003c/b\u003e and becomes \u003cb\u003eR. Saturnino de Brito\u003c/b\u003e",
                     "polyline" : {
                        "points" : "`tpxBbeekGCFELADCDABC@C@E@UB}AS"
                     },
                     "start_location" : {
                        "lat" : -19.9150547,
                        "lng" : -43.9408238
                     },
                     "travel_mode" : "DRIVING"
                  },
                  {
                     "distance" : {
                        "text" : "0.1 km",
                        "value" : 122
                     },
                     "duration" : {
                        "text" : "1 min",
                        "value" : 46
                     },
                     "end_location" : {
                        "lat" : -19.9140985,
                        "lng" : -43.9417671
                     },
                     "html_instructions" : "Turn \u003cb\u003eleft\u003c/b\u003e\u003cdiv style=\"font-size:0.9em\"\u003eDestination will be on the right\u003c/div\u003e",
                     "maneuver" : "turn-left",
                     "polyline" : {
                        "points" : "lopxB~eekGIFGFOHw@`@CB?@?@?@?@@Bp@tA"
                     },
                     "start_location" : {
                        "lat" : -19.9143135,
                        "lng" : -43.9409559
                     },
                     "travel_mode" : "DRIVING"
                  }
               ],
               "traffic_speed_entry" : [],
               "via_waypoint" : []
            }
         ],
         "overview_polyline" : {
            "points" : "bnpxB`kekGp@pALAv@a@HAzBXTFVHxFdA`@eDV{ARmAl@JpF~@`FbAfGbAl@HtAV`@FXLTFNAPDfARpAXx@L~HrAdCd@}EnCi@\\w@\\gCzAEEQUa@[SI_@Is@AWDi@V]b@[t@Gb@A^B^HX\\p@PT\\Rd@JX?t@GVK`AtBzB|Ez@nB^p@tA~CnApCkB]kB]RkAh@sDDUcBkD]u@{@eBuA{C`@e@Tm@F_@@[Iw@K[KOe@g@UM_@Mq@EYBWHe@XOP[n@ObA?^F\\DJgAl@iCtAuBdAeCzAQJ}A]oE_AgCa@c@AQAu@q@qEuDm@i@m@g@g@Sc@Ic@CkBDq@Kg@SYWM[e@wAiBsDCUy@iBgA_Cq@aBGKMGW}AUqBJcAH[Dg@DQdBqKNsA?oGGkI?eDBsAFg@`@_DPiALQf@YVMNGb@bAp@fB\\Rj@pAx@|Af@bAfBdE\\XVCdBXRf@wBbNaBhKjDj@vEz@|AXt@NTZTOxBmAbDuAf@YnHiE~Ct@ZHXFh@eECGa@e@i@T}BnAgAr@[Na@GyDs@iFaAeGeAcDm@uCg@a@`C_A`G_@`ChAPtATrAV`F|@JBBJBJCNGNeDbBw@d@MDMBI?_C[MAGn@Gl@CFGREHc@H}ASIFWP{@f@?Dr@xA"
         },
         "summary" : "R. Curitiba",
         "warnings" : [],
         "waypoint_order" : [ 0, 1, 2, 3, 4, 5 ]
      }
   ],
   "status" : "OK"
}
