{
   "geocoded_waypoints" : [
      {
         "geocoder_status" : "OK",
         "place_id" : "ChIJbfevC_6ZpgAR_R-g4-MuUFk",
         "types" : [ "street_address" ]
      },
      {
         "geocoder_status" : "OK",
         "place_id" : "ChIJgQBmWfuZpgAR30cD4lINtkI",
         "types" : [ "establishment", "point_of_interest", "premise" ]
      },
      {
         "geocoder_status" : "OK",
         "place_id" : "ChIJuyXL-PmZpgARjmiyFx2UJlE",
         "types" : [ "street_address" ]
      },
      {
         "geocoder_status" : "OK",
         "place_id" : "ChIJXX_Nvu2ZpgARtUylzw3KPu4",
         "types" : [ "street_address" ]
      },
      {
         "geocoder_status" : "OK",
         "place_id" : "ChIJuyXL-PmZpgARjmiyFx2UJlE",
         "types" : [ "street_address" ]
      },
      {
         "geocoder_status" : "OK",
         "place_id" : "ChIJE_AciR2apgARPxS5vTrU42w",
         "types" : [ "street_address" ]
      },
      {
         "geocoder_status" : "OK",
         "place_id" : "ChIJedAMjViXpgARNgo5SyFMQ2Y",
         "types" : [ "street_address" ]
      },
      {
         "geocoder_status" : "OK",
         "place_id" : "ChIJgQBmWfuZpgAR30cD4lINtkI",
         "types" : [ "establishment", "point_of_interest", "premise" ]
      },
      {
         "geocoder_status" : "OK",
         "place_id" : "EkdSdWEgR3VhaWN1cnVzLCAzNDgtMzU0IC0gQ2VudHJvLCBCZWxvIEhvcml6b250ZSAtIE1HLCAzMDExMS0wNjAsIEJyYXNpbA",
         "types" : [ "street_address" ]
      },
      {
         "geocoder_status" : "OK",
         "place_id" : "ChIJbfevC_6ZpgAR_R-g4-MuUFk",
         "types" : [ "street_address" ]
      }
   ],
   "routes" : [
      {
         "bounds" : {
            "northeast" : {
               "lat" : -19.9121439,
               "lng" : -43.9272023
            },
            "southwest" : {
               "lat" : -19.9258142,
               "lng" : -43.94610309999999
            }
         },
         "copyrights" : "Map data ©2017 Google",
         "legs" : [
            {
               "distance" : {
                  "text" : "0.8 km",
                  "value" : 780
               },
               "duration" : {
                  "text" : "3 mins",
                  "value" : 203
               },
               "end_address" : "Obelisco Praça Sete - Av. Afonso Pena - Centro, Belo Horizonte - MG, 31840-190, Brazil",
               "end_location" : {
                  "lat" : -19.9191852,
                  "lng" : -43.9387306
               },
               "start_address" : "Av. do Contorno, 340 - Santa Efigênia, Belo Horizonte - MG, 30110-017, Brazil",
               "start_location" : {
                  "lat" : -19.9140985,
                  "lng" : -43.9417671
               },
               "steps" : [
                  {
                     "distance" : {
                        "text" : "0.1 km",
                        "value" : 107
                     },
                     "duration" : {
                        "text" : "1 min",
                        "value" : 38
                     },
                     "end_location" : {
                        "lat" : -19.9147983,
                        "lng" : -43.9420035
                     },
                     "html_instructions" : "Head \u003cb\u003esouthwest\u003c/b\u003e toward \u003cb\u003eR. Paulo de Frontin\u003c/b\u003e",
                     "polyline" : {
                        "points" : "bnpxB`kekGl@nA@??@@?@?B?B?BAp@_@DABAD?H@"
                     },
                     "start_location" : {
                        "lat" : -19.9140985,
                        "lng" : -43.9417671
                     },
                     "travel_mode" : "DRIVING"
                  },
                  {
                     "distance" : {
                        "text" : "92 m",
                        "value" : 92
                     },
                     "duration" : {
                        "text" : "1 min",
                        "value" : 26
                     },
                     "end_location" : {
                        "lat" : -19.9156,
                        "lng" : -43.94221049999999
                     },
                     "html_instructions" : "Continue onto \u003cb\u003eRua dos Guaranis\u003c/b\u003e",
                     "polyline" : {
                        "points" : "nrpxBnlekGpBVLBFBVH"
                     },
                     "start_location" : {
                        "lat" : -19.9147983,
                        "lng" : -43.9420035
                     },
                     "travel_mode" : "DRIVING"
                  },
                  {
                     "distance" : {
                        "text" : "0.2 km",
                        "value" : 173
                     },
                     "duration" : {
                        "text" : "1 min",
                        "value" : 43
                     },
                     "end_location" : {
                        "lat" : -19.915984,
                        "lng" : -43.9406129
                     },
                     "html_instructions" : "Turn \u003cb\u003eleft\u003c/b\u003e onto \u003cb\u003eRua dos Caetés\u003c/b\u003e",
                     "maneuver" : "turn-left",
                     "polyline" : {
                        "points" : "nwpxBxmekGDWDYZeBBI@IJ_APsA"
                     },
                     "start_location" : {
                        "lat" : -19.9156,
                        "lng" : -43.94221049999999
                     },
                     "travel_mode" : "DRIVING"
                  },
                  {
                     "distance" : {
                        "text" : "0.4 km",
                        "value" : 408
                     },
                     "duration" : {
                        "text" : "2 mins",
                        "value" : 96
                     },
                     "end_location" : {
                        "lat" : -19.9191852,
                        "lng" : -43.9387306
                     },
                     "html_instructions" : "Turn \u003cb\u003eright\u003c/b\u003e onto \u003cb\u003eAv. Afonso Pena\u003c/b\u003e\u003cdiv style=\"font-size:0.9em\"\u003eDestination will be on the left\u003c/div\u003e",
                     "maneuver" : "turn-right",
                     "polyline" : {
                        "points" : "zypxBxcekG\\EfCsApC{AFELIv@_@`Am@dCcA\\QTM"
                     },
                     "start_location" : {
                        "lat" : -19.915984,
                        "lng" : -43.9406129
                     },
                     "travel_mode" : "DRIVING"
                  }
               ],
               "traffic_speed_entry" : [],
               "via_waypoint" : []
            },
            {
               "distance" : {
                  "text" : "1.7 km",
                  "value" : 1733
               },
               "duration" : {
                  "text" : "6 mins",
                  "value" : 388
               },
               "end_address" : "Av. dos Andradas, 128 - Centro, Belo Horizonte - MG, 30120-010, Brazil",
               "end_location" : {
                  "lat" : -19.9166804,
                  "lng" : -43.9344971
               },
               "start_address" : "Obelisco Praça Sete - Av. Afonso Pena - Centro, Belo Horizonte - MG, 31840-190, Brazil",
               "start_location" : {
                  "lat" : -19.9191852,
                  "lng" : -43.9387306
               },
               "steps" : [
                  {
                     "distance" : {
                        "text" : "0.2 km",
                        "value" : 212
                     },
                     "duration" : {
                        "text" : "1 min",
                        "value" : 36
                     },
                     "end_location" : {
                        "lat" : -19.920802,
                        "lng" : -43.937665
                     },
                     "html_instructions" : "Head \u003cb\u003esoutheast\u003c/b\u003e on \u003cb\u003eAv. Afonso Pena\u003c/b\u003e toward \u003cb\u003eAv. Amazonas\u003c/b\u003e",
                     "polyline" : {
                        "points" : "|mqxB`xdkGPKPMtDuBfAm@^W"
                     },
                     "start_location" : {
                        "lat" : -19.9191852,
                        "lng" : -43.9387306
                     },
                     "travel_mode" : "DRIVING"
                  },
                  {
                     "distance" : {
                        "text" : "0.1 km",
                        "value" : 124
                     },
                     "duration" : {
                        "text" : "1 min",
                        "value" : 32
                     },
                     "end_location" : {
                        "lat" : -19.9218666,
                        "lng" : -43.9380169
                     },
                     "html_instructions" : "Turn \u003cb\u003eright\u003c/b\u003e onto \u003cb\u003eR. Espírito Santo\u003c/b\u003e (signs for \u003cb\u003eViad. Santa Tereza\u003c/b\u003e/\u003cb\u003eAeroporto Internacional\u003c/b\u003e)",
                     "maneuver" : "turn-right",
                     "polyline" : {
                        "points" : "~wqxBjqdkGv@RfB`@FDRBXF"
                     },
                     "start_location" : {
                        "lat" : -19.920802,
                        "lng" : -43.937665
                     },
                     "travel_mode" : "DRIVING"
                  },
                  {
                     "distance" : {
                        "text" : "0.1 km",
                        "value" : 119
                     },
                     "duration" : {
                        "text" : "1 min",
                        "value" : 34
                     },
                     "end_location" : {
                        "lat" : -19.9220184,
                        "lng" : -43.9369264
                     },
                     "html_instructions" : "Turn \u003cb\u003eleft\u003c/b\u003e at the 1st cross street onto \u003cb\u003eRua dos Tupis\u003c/b\u003e",
                     "maneuver" : "turn-left",
                     "polyline" : {
                        "points" : "t~qxBrsdkGh@eEACACCECE"
                     },
                     "start_location" : {
                        "lat" : -19.9218666,
                        "lng" : -43.9380169
                     },
                     "travel_mode" : "DRIVING"
                  },
                  {
                     "distance" : {
                        "text" : "0.2 km",
                        "value" : 193
                     },
                     "duration" : {
                        "text" : "1 min",
                        "value" : 34
                     },
                     "end_location" : {
                        "lat" : -19.9205475,
                        "lng" : -43.9376498
                     },
                     "html_instructions" : "Turn \u003cb\u003eleft\u003c/b\u003e at the 1st cross street onto \u003cb\u003eAv. Afonso Pena\u003c/b\u003e",
                     "maneuver" : "turn-left",
                     "polyline" : {
                        "points" : "r_rxBxldkGYYOJYHaAh@{@d@a@Xe@X[N"
                     },
                     "start_location" : {
                        "lat" : -19.9220184,
                        "lng" : -43.9369264
                     },
                     "travel_mode" : "DRIVING"
                  },
                  {
                     "distance" : {
                        "text" : "0.7 km",
                        "value" : 693
                     },
                     "duration" : {
                        "text" : "3 mins",
                        "value" : 164
                     },
                     "end_location" : {
                        "lat" : -19.914509,
                        "lng" : -43.9360148
                     },
                     "html_instructions" : "Turn \u003cb\u003eright\u003c/b\u003e onto \u003cb\u003eR. Espírito Santo\u003c/b\u003e (signs for \u003cb\u003eAv. Crist. Machado\u003c/b\u003e/\u003cb\u003ePampulha\u003c/b\u003e/\u003cb\u003eAerop. Internacional\u003c/b\u003e/\u003cb\u003eVitória\u003c/b\u003e)",
                     "maneuver" : "turn-right",
                     "polyline" : {
                        "points" : "lvqxBhqdkGa@GiCg@o@KiCe@_B[WCs@Ou@McCc@mAUcASIAGAkASiASyAUwAW"
                     },
                     "start_location" : {
                        "lat" : -19.9205475,
                        "lng" : -43.9376498
                     },
                     "travel_mode" : "DRIVING"
                  },
                  {
                     "distance" : {
                        "text" : "0.2 km",
                        "value" : 212
                     },
                     "duration" : {
                        "text" : "1 min",
                        "value" : 45
                     },
                     "end_location" : {
                        "lat" : -19.9151124,
                        "lng" : -43.93413169999999
                     },
                     "html_instructions" : "Turn \u003cb\u003eright\u003c/b\u003e onto \u003cb\u003eAv. do Contorno\u003c/b\u003e",
                     "maneuver" : "turn-right",
                     "polyline" : {
                        "points" : "tppxB`gdkG\\gC\\gCJ]BMFQDIHIBENO"
                     },
                     "start_location" : {
                        "lat" : -19.914509,
                        "lng" : -43.9360148
                     },
                     "travel_mode" : "DRIVING"
                  },
                  {
                     "distance" : {
                        "text" : "0.2 km",
                        "value" : 180
                     },
                     "duration" : {
                        "text" : "1 min",
                        "value" : 43
                     },
                     "end_location" : {
                        "lat" : -19.9166804,
                        "lng" : -43.9344971
                     },
                     "html_instructions" : "\u003cb\u003eAv. do Contorno\u003c/b\u003e turns \u003cb\u003eright\u003c/b\u003e and becomes \u003cb\u003eAv. dos Andradas\u003c/b\u003e\u003cdiv style=\"font-size:0.9em\"\u003eDestination will be on the right\u003c/div\u003e",
                     "polyline" : {
                        "points" : "ltpxBh{ckGPCD?h@Hz@NZDVFlB\\PBFB"
                     },
                     "start_location" : {
                        "lat" : -19.9151124,
                        "lng" : -43.93413169999999
                     },
                     "travel_mode" : "DRIVING"
                  }
               ],
               "traffic_speed_entry" : [],
               "via_waypoint" : []
            },
            {
               "distance" : {
                  "text" : "1.8 km",
                  "value" : 1838
               },
               "duration" : {
                  "text" : "5 mins",
                  "value" : 318
               },
               "end_address" : "Av. Prof. Alfredo Balena, 110 - Santa Efigênia, Belo Horizonte - MG, 30130-100, Brazil",
               "end_location" : {
                  "lat" : -19.9242151,
                  "lng" : -43.9286409
               },
               "start_address" : "Av. dos Andradas, 128 - Centro, Belo Horizonte - MG, 30120-010, Brazil",
               "start_location" : {
                  "lat" : -19.9166804,
                  "lng" : -43.9344971
               },
               "steps" : [
                  {
                     "distance" : {
                        "text" : "0.3 km",
                        "value" : 299
                     },
                     "duration" : {
                        "text" : "1 min",
                        "value" : 45
                     },
                     "end_location" : {
                        "lat" : -19.9192729,
                        "lng" : -43.9352656
                     },
                     "html_instructions" : "Head \u003cb\u003esouth\u003c/b\u003e on \u003cb\u003eAv. dos Andradas\u003c/b\u003e toward \u003cb\u003eRua dos Caetés\u003c/b\u003e",
                     "polyline" : {
                        "points" : "f~pxBr}ckGF@NBx@Pj@J\\F~A^pCj@rB^B@"
                     },
                     "start_location" : {
                        "lat" : -19.9166804,
                        "lng" : -43.9344971
                     },
                     "travel_mode" : "DRIVING"
                  },
                  {
                     "distance" : {
                        "text" : "0.9 km",
                        "value" : 879
                     },
                     "duration" : {
                        "text" : "2 mins",
                        "value" : 114
                     },
                     "end_location" : {
                        "lat" : -19.9212657,
                        "lng" : -43.9287193
                     },
                     "html_instructions" : "Slight \u003cb\u003eleft\u003c/b\u003e to stay on \u003cb\u003eAv. dos Andradas\u003c/b\u003e",
                     "maneuver" : "turn-slight-left",
                     "polyline" : {
                        "points" : "lnqxBlbdkGLAV@R?J?J?LAJAXGd@QHEHE@?FCFEjAm@d@WTMLOLMJSp@}AbAaC`@_ATm@J_@F_@Ha@Bq@Am@KkAA[EY]wAmAkEs@_CAGCKEY"
                     },
                     "start_location" : {
                        "lat" : -19.9192729,
                        "lng" : -43.9352656
                     },
                     "travel_mode" : "DRIVING"
                  },
                  {
                     "distance" : {
                        "text" : "0.3 km",
                        "value" : 266
                     },
                     "duration" : {
                        "text" : "1 min",
                        "value" : 49
                     },
                     "end_location" : {
                        "lat" : -19.9232736,
                        "lng" : -43.9273471
                     },
                     "html_instructions" : "Turn \u003cb\u003eright\u003c/b\u003e onto \u003cb\u003eAv. Francisco Sales\u003c/b\u003e",
                     "maneuver" : "turn-right",
                     "polyline" : {
                        "points" : "|zqxBnybkGHKDGFGZQZQXQJEh@[h@Yj@]PORObBy@NK"
                     },
                     "start_location" : {
                        "lat" : -19.9212657,
                        "lng" : -43.9287193
                     },
                     "travel_mode" : "DRIVING"
                  },
                  {
                     "distance" : {
                        "text" : "0.1 km",
                        "value" : 120
                     },
                     "duration" : {
                        "text" : "1 min",
                        "value" : 24
                     },
                     "end_location" : {
                        "lat" : -19.9242886,
                        "lng" : -43.9276434
                     },
                     "html_instructions" : "Turn \u003cb\u003eright\u003c/b\u003e onto \u003cb\u003eAv. Bernardo Monteiro\u003c/b\u003e",
                     "maneuver" : "turn-right",
                     "polyline" : {
                        "points" : "lgrxB|pbkGPNBDDBFBJBZB|@HT@j@F"
                     },
                     "start_location" : {
                        "lat" : -19.9232736,
                        "lng" : -43.9273471
                     },
                     "travel_mode" : "DRIVING"
                  },
                  {
                     "distance" : {
                        "text" : "0.2 km",
                        "value" : 162
                     },
                     "duration" : {
                        "text" : "1 min",
                        "value" : 46
                     },
                     "end_location" : {
                        "lat" : -19.9250157,
                        "lng" : -43.9289818
                     },
                     "html_instructions" : "Turn \u003cb\u003eright\u003c/b\u003e onto \u003cb\u003eAv. Prof. Alfredo Balena\u003c/b\u003e",
                     "maneuver" : "turn-right",
                     "polyline" : {
                        "points" : "xmrxBvrbkGL\\Xl@P`@HPFNLVN\\FLHPHPJR"
                     },
                     "start_location" : {
                        "lat" : -19.9242886,
                        "lng" : -43.9276434
                     },
                     "travel_mode" : "DRIVING"
                  },
                  {
                     "distance" : {
                        "text" : "6 m",
                        "value" : 6
                     },
                     "duration" : {
                        "text" : "1 min",
                        "value" : 8
                     },
                     "end_location" : {
                        "lat" : -19.9249687,
                        "lng" : -43.9290145
                     },
                     "html_instructions" : "Turn \u003cb\u003eright\u003c/b\u003e",
                     "maneuver" : "turn-right",
                     "polyline" : {
                        "points" : "jrrxBb{bkGID"
                     },
                     "start_location" : {
                        "lat" : -19.9250157,
                        "lng" : -43.9289818
                     },
                     "travel_mode" : "DRIVING"
                  },
                  {
                     "distance" : {
                        "text" : "72 m",
                        "value" : 72
                     },
                     "duration" : {
                        "text" : "1 min",
                        "value" : 23
                     },
                     "end_location" : {
                        "lat" : -19.9243802,
                        "lng" : -43.928919
                     },
                     "html_instructions" : "Turn \u003cb\u003eright\u003c/b\u003e",
                     "maneuver" : "turn-right",
                     "polyline" : {
                        "points" : "`rrxBh{bkGIICCECGCGAAAA?CAEAC?GAE?E?C?IBMBC@KB"
                     },
                     "start_location" : {
                        "lat" : -19.9249687,
                        "lng" : -43.9290145
                     },
                     "travel_mode" : "DRIVING"
                  },
                  {
                     "distance" : {
                        "text" : "34 m",
                        "value" : 34
                     },
                     "duration" : {
                        "text" : "1 min",
                        "value" : 9
                     },
                     "end_location" : {
                        "lat" : -19.9242151,
                        "lng" : -43.9286409
                     },
                     "html_instructions" : "Turn \u003cb\u003eright\u003c/b\u003e",
                     "maneuver" : "turn-right",
                     "polyline" : {
                        "points" : "jnrxBvzbkG_@w@"
                     },
                     "start_location" : {
                        "lat" : -19.9243802,
                        "lng" : -43.928919
                     },
                     "travel_mode" : "DRIVING"
                  }
               ],
               "traffic_speed_entry" : [],
               "via_waypoint" : []
            },
            {
               "distance" : {
                  "text" : "2.5 km",
                  "value" : 2466
               },
               "duration" : {
                  "text" : "9 mins",
                  "value" : 524
               },
               "end_address" : "Av. dos Andradas, 128 - Centro, Belo Horizonte - MG, 30120-010, Brazil",
               "end_location" : {
                  "lat" : -19.9166804,
                  "lng" : -43.9344971
               },
               "start_address" : "Av. Prof. Alfredo Balena, 110 - Santa Efigênia, Belo Horizonte - MG, 30130-100, Brazil",
               "start_location" : {
                  "lat" : -19.9242151,
                  "lng" : -43.9286409
               },
               "steps" : [
                  {
                     "distance" : {
                        "text" : "34 m",
                        "value" : 34
                     },
                     "duration" : {
                        "text" : "1 min",
                        "value" : 8
                     },
                     "end_location" : {
                        "lat" : -19.9243802,
                        "lng" : -43.928919
                     },
                     "html_instructions" : "Head \u003cb\u003esouthwest\u003c/b\u003e",
                     "polyline" : {
                        "points" : "jmrxB~xbkG^v@"
                     },
                     "start_location" : {
                        "lat" : -19.9242151,
                        "lng" : -43.9286409
                     },
                     "travel_mode" : "DRIVING"
                  },
                  {
                     "distance" : {
                        "text" : "7 m",
                        "value" : 7
                     },
                     "duration" : {
                        "text" : "1 min",
                        "value" : 6
                     },
                     "end_location" : {
                        "lat" : -19.924444,
                        "lng" : -43.9288963
                     },
                     "html_instructions" : "Turn \u003cb\u003eleft\u003c/b\u003e toward \u003cb\u003eAv. Prof. Alfredo Balena\u003c/b\u003e",
                     "maneuver" : "turn-left",
                     "polyline" : {
                        "points" : "jnrxBvzbkGJC"
                     },
                     "start_location" : {
                        "lat" : -19.9243802,
                        "lng" : -43.928919
                     },
                     "travel_mode" : "DRIVING"
                  },
                  {
                     "distance" : {
                        "text" : "0.2 km",
                        "value" : 198
                     },
                     "duration" : {
                        "text" : "1 min",
                        "value" : 56
                     },
                     "end_location" : {
                        "lat" : -19.925045,
                        "lng" : -43.9305761
                     },
                     "html_instructions" : "Turn \u003cb\u003eright\u003c/b\u003e toward \u003cb\u003eAv. Prof. Alfredo Balena\u003c/b\u003e",
                     "maneuver" : "turn-right",
                     "polyline" : {
                        "points" : "vnrxBrzbkG^v@Rb@Tf@CHGPELAL?F@FJXn@~ABH"
                     },
                     "start_location" : {
                        "lat" : -19.924444,
                        "lng" : -43.9288963
                     },
                     "travel_mode" : "DRIVING"
                  },
                  {
                     "distance" : {
                        "text" : "84 m",
                        "value" : 84
                     },
                     "duration" : {
                        "text" : "1 min",
                        "value" : 32
                     },
                     "end_location" : {
                        "lat" : -19.9257197,
                        "lng" : -43.9302311
                     },
                     "html_instructions" : "Turn \u003cb\u003eleft\u003c/b\u003e toward \u003cb\u003eAv. Prof. Alfredo Balena\u003c/b\u003e",
                     "maneuver" : "turn-left",
                     "polyline" : {
                        "points" : "nrrxBbeckGPA\\QvAq@"
                     },
                     "start_location" : {
                        "lat" : -19.925045,
                        "lng" : -43.9305761
                     },
                     "travel_mode" : "DRIVING"
                  },
                  {
                     "distance" : {
                        "text" : "0.3 km",
                        "value" : 333
                     },
                     "duration" : {
                        "text" : "2 mins",
                        "value" : 92
                     },
                     "end_location" : {
                        "lat" : -19.9243624,
                        "lng" : -43.92753219999999
                     },
                     "html_instructions" : "Turn \u003cb\u003eleft\u003c/b\u003e onto \u003cb\u003eAv. Prof. Alfredo Balena\u003c/b\u003e",
                     "maneuver" : "turn-left",
                     "polyline" : {
                        "points" : "vvrxB|bckGPGIWACKUUi@IUIOACGOGOCEEICGMUGIIOEKOWGQIQIMAGKUMWGQIOQc@KUISACEGO]"
                     },
                     "start_location" : {
                        "lat" : -19.9257197,
                        "lng" : -43.9302311
                     },
                     "travel_mode" : "DRIVING"
                  },
                  {
                     "distance" : {
                        "text" : "0.1 km",
                        "value" : 117
                     },
                     "duration" : {
                        "text" : "1 min",
                        "value" : 31
                     },
                     "end_location" : {
                        "lat" : -19.9233562,
                        "lng" : -43.9272931
                     },
                     "html_instructions" : "Turn \u003cb\u003eleft\u003c/b\u003e onto \u003cb\u003eAv. Bernardo Monteiro\u003c/b\u003e",
                     "maneuver" : "turn-left",
                     "polyline" : {
                        "points" : "fnrxB`rbkGY?w@Gw@IMAMAICECCAMO"
                     },
                     "start_location" : {
                        "lat" : -19.9243624,
                        "lng" : -43.92753219999999
                     },
                     "travel_mode" : "DRIVING"
                  },
                  {
                     "distance" : {
                        "text" : "0.1 km",
                        "value" : 107
                     },
                     "duration" : {
                        "text" : "1 min",
                        "value" : 16
                     },
                     "end_location" : {
                        "lat" : -19.9225303,
                        "lng" : -43.9276381
                     },
                     "html_instructions" : "Turn \u003cb\u003eleft\u003c/b\u003e onto \u003cb\u003eAv. Francisco Sales\u003c/b\u003e",
                     "maneuver" : "turn-left",
                     "polyline" : {
                        "points" : "~grxBppbkGQGOIOJGBGDGDULUHo@b@"
                     },
                     "start_location" : {
                        "lat" : -19.9233562,
                        "lng" : -43.9272931
                     },
                     "travel_mode" : "DRIVING"
                  },
                  {
                     "distance" : {
                        "text" : "0.9 km",
                        "value" : 919
                     },
                     "duration" : {
                        "text" : "2 mins",
                        "value" : 125
                     },
                     "end_location" : {
                        "lat" : -19.9153876,
                        "lng" : -43.9320633
                     },
                     "html_instructions" : "Keep \u003cb\u003eleft\u003c/b\u003e to continue on \u003cb\u003eAv. Francisco Sales\u003c/b\u003e/\u003cb\u003eViaduto Francisco Sales\u003c/b\u003e\u003cdiv style=\"font-size:0.9em\"\u003eContinue to follow Av. Francisco Sales\u003c/div\u003e",
                     "maneuver" : "keep-left",
                     "polyline" : {
                        "points" : "xbrxBvrbkGOLeCtAu@b@k@\\g@Xi@VaAh@yAt@{@b@kB|@q@Zq@Zk@XyBhAm@\\o@\\y@d@sAr@wAt@yAv@_@R}@d@"
                     },
                     "start_location" : {
                        "lat" : -19.9225303,
                        "lng" : -43.9276381
                     },
                     "travel_mode" : "DRIVING"
                  },
                  {
                     "distance" : {
                        "text" : "0.2 km",
                        "value" : 169
                     },
                     "duration" : {
                        "text" : "1 min",
                        "value" : 39
                     },
                     "end_location" : {
                        "lat" : -19.9139204,
                        "lng" : -43.9316513
                     },
                     "html_instructions" : "Turn \u003cb\u003eright\u003c/b\u003e onto \u003cb\u003eR. Sapucaí\u003c/b\u003e",
                     "maneuver" : "turn-right",
                     "polyline" : {
                        "points" : "dvpxBjnckGs@K]IoAUaAUSC[EQE"
                     },
                     "start_location" : {
                        "lat" : -19.9153876,
                        "lng" : -43.9320633
                     },
                     "travel_mode" : "DRIVING"
                  },
                  {
                     "distance" : {
                        "text" : "27 m",
                        "value" : 27
                     },
                     "duration" : {
                        "text" : "1 min",
                        "value" : 19
                     },
                     "end_location" : {
                        "lat" : -19.9137258,
                        "lng" : -43.931794
                     },
                     "html_instructions" : "Turn \u003cb\u003eleft\u003c/b\u003e to stay on \u003cb\u003eR. Sapucaí\u003c/b\u003e",
                     "maneuver" : "turn-left",
                     "polyline" : {
                        "points" : "~lpxBxkckGE@GBMHIJ"
                     },
                     "start_location" : {
                        "lat" : -19.9139204,
                        "lng" : -43.9316513
                     },
                     "travel_mode" : "DRIVING"
                  },
                  {
                     "distance" : {
                        "text" : "0.3 km",
                        "value" : 269
                     },
                     "duration" : {
                        "text" : "1 min",
                        "value" : 52
                     },
                     "end_location" : {
                        "lat" : -19.9149596,
                        "lng" : -43.9340008
                     },
                     "html_instructions" : "Turn \u003cb\u003eleft\u003c/b\u003e onto \u003cb\u003eAv. do Contorno\u003c/b\u003e",
                     "maneuver" : "turn-left",
                     "polyline" : {
                        "points" : "xkpxBtlckGj@pAXj@^p@^p@FP^|@h@lAL\\NZ"
                     },
                     "start_location" : {
                        "lat" : -19.9137258,
                        "lng" : -43.931794
                     },
                     "travel_mode" : "DRIVING"
                  },
                  {
                     "distance" : {
                        "text" : "0.2 km",
                        "value" : 202
                     },
                     "duration" : {
                        "text" : "1 min",
                        "value" : 48
                     },
                     "end_location" : {
                        "lat" : -19.9166804,
                        "lng" : -43.9344971
                     },
                     "html_instructions" : "\u003cb\u003eAv. do Contorno\u003c/b\u003e turns \u003cb\u003eleft\u003c/b\u003e and becomes \u003cb\u003eAv. dos Andradas\u003c/b\u003e\u003cdiv style=\"font-size:0.9em\"\u003eDestination will be on the right\u003c/div\u003e",
                     "polyline" : {
                        "points" : "nspxBnzckGPLJJPCD?h@Hz@NZDVFlB\\PBFB"
                     },
                     "start_location" : {
                        "lat" : -19.9149596,
                        "lng" : -43.9340008
                     },
                     "travel_mode" : "DRIVING"
                  }
               ],
               "traffic_speed_entry" : [],
               "via_waypoint" : []
            },
            {
               "distance" : {
                  "text" : "2.0 km",
                  "value" : 1952
               },
               "duration" : {
                  "text" : "6 mins",
                  "value" : 352
               },
               "end_address" : "R. Célio de Castro, 869 - Floresta, Belo Horizonte - MG, Brazil",
               "end_location" : {
                  "lat" : -19.9127637,
                  "lng" : -43.9310629
               },
               "start_address" : "Av. dos Andradas, 128 - Centro, Belo Horizonte - MG, 30120-010, Brazil",
               "start_location" : {
                  "lat" : -19.9166804,
                  "lng" : -43.9344971
               },
               "steps" : [
                  {
                     "distance" : {
                        "text" : "90 m",
                        "value" : 90
                     },
                     "duration" : {
                        "text" : "1 min",
                        "value" : 17
                     },
                     "end_location" : {
                        "lat" : -19.9174587,
                        "lng" : -43.9347238
                     },
                     "html_instructions" : "Head \u003cb\u003esouth\u003c/b\u003e on \u003cb\u003eAv. dos Andradas\u003c/b\u003e toward \u003cb\u003eRua dos Caetés\u003c/b\u003e",
                     "polyline" : {
                        "points" : "f~pxBr}ckGF@NBx@Pj@J\\F"
                     },
                     "start_location" : {
                        "lat" : -19.9166804,
                        "lng" : -43.9344971
                     },
                     "travel_mode" : "DRIVING"
                  },
                  {
                     "distance" : {
                        "text" : "74 m",
                        "value" : 74
                     },
                     "duration" : {
                        "text" : "1 min",
                        "value" : 18
                     },
                     "end_location" : {
                        "lat" : -19.9174066,
                        "lng" : -43.9353914
                     },
                     "html_instructions" : "Turn \u003cb\u003eright\u003c/b\u003e onto \u003cb\u003eRua dos Caetés\u003c/b\u003e",
                     "maneuver" : "turn-right",
                     "polyline" : {
                        "points" : "bcqxB~~ckGCPKh@G\\?D?B?F@D?DBBFH"
                     },
                     "start_location" : {
                        "lat" : -19.9174587,
                        "lng" : -43.9347238
                     },
                     "travel_mode" : "DRIVING"
                  },
                  {
                     "distance" : {
                        "text" : "0.1 km",
                        "value" : 128
                     },
                     "duration" : {
                        "text" : "1 min",
                        "value" : 28
                     },
                     "end_location" : {
                        "lat" : -19.9185154,
                        "lng" : -43.9357179
                     },
                     "html_instructions" : "\u003cb\u003eRua dos Caetés\u003c/b\u003e turns \u003cb\u003eleft\u003c/b\u003e and becomes \u003cb\u003eR. da Bahia\u003c/b\u003e",
                     "polyline" : {
                        "points" : "xbqxBdcdkGxDv@b@H"
                     },
                     "start_location" : {
                        "lat" : -19.9174066,
                        "lng" : -43.9353914
                     },
                     "travel_mode" : "DRIVING"
                  },
                  {
                     "distance" : {
                        "text" : "67 m",
                        "value" : 67
                     },
                     "duration" : {
                        "text" : "1 min",
                        "value" : 40
                     },
                     "end_location" : {
                        "lat" : -19.9186684,
                        "lng" : -43.935096
                     },
                     "html_instructions" : "Turn \u003cb\u003eleft\u003c/b\u003e onto \u003cb\u003eRua dos Tupinambás\u003c/b\u003e",
                     "maneuver" : "turn-left",
                     "polyline" : {
                        "points" : "viqxBfedkGL}@N}@"
                     },
                     "start_location" : {
                        "lat" : -19.9185154,
                        "lng" : -43.9357179
                     },
                     "travel_mode" : "DRIVING"
                  },
                  {
                     "distance" : {
                        "text" : "0.5 km",
                        "value" : 451
                     },
                     "duration" : {
                        "text" : "1 min",
                        "value" : 81
                     },
                     "end_location" : {
                        "lat" : -19.9149596,
                        "lng" : -43.9340008
                     },
                     "html_instructions" : "Turn \u003cb\u003eleft\u003c/b\u003e at the 1st cross street onto \u003cb\u003eAv. dos Andradas\u003c/b\u003e",
                     "maneuver" : "turn-left",
                     "polyline" : {
                        "points" : "tjqxBjadkGBQBSqFgAUI{Bc@GAIAwCg@KCSEYEYESEQAE?Y@O@UD"
                     },
                     "start_location" : {
                        "lat" : -19.9186684,
                        "lng" : -43.935096
                     },
                     "travel_mode" : "DRIVING"
                  },
                  {
                     "distance" : {
                        "text" : "0.3 km",
                        "value" : 314
                     },
                     "duration" : {
                        "text" : "1 min",
                        "value" : 46
                     },
                     "end_location" : {
                        "lat" : -19.9141482,
                        "lng" : -43.9368585
                     },
                     "html_instructions" : "\u003cb\u003eAv. dos Andradas\u003c/b\u003e turns \u003cb\u003eleft\u003c/b\u003e and becomes \u003cb\u003eAv. do Contorno\u003c/b\u003e",
                     "polyline" : {
                        "points" : "nspxBnzckGU\\INI^IXIVc@vCa@tCUpBGZ"
                     },
                     "start_location" : {
                        "lat" : -19.9149596,
                        "lng" : -43.9340008
                     },
                     "travel_mode" : "DRIVING"
                  },
                  {
                     "distance" : {
                        "text" : "43 m",
                        "value" : 43
                     },
                     "duration" : {
                        "text" : "1 min",
                        "value" : 4
                     },
                     "end_location" : {
                        "lat" : -19.9139483,
                        "lng" : -43.9372076
                     },
                     "html_instructions" : "Slight \u003cb\u003eright\u003c/b\u003e to stay on \u003cb\u003eAv. do Contorno\u003c/b\u003e",
                     "maneuver" : "turn-slight-right",
                     "polyline" : {
                        "points" : "lnpxBjldkGg@dA"
                     },
                     "start_location" : {
                        "lat" : -19.9141482,
                        "lng" : -43.9368585
                     },
                     "travel_mode" : "DRIVING"
                  },
                  {
                     "distance" : {
                        "text" : "0.2 km",
                        "value" : 177
                     },
                     "duration" : {
                        "text" : "1 min",
                        "value" : 23
                     },
                     "end_location" : {
                        "lat" : -19.9124036,
                        "lng" : -43.9368048
                     },
                     "html_instructions" : "Turn \u003cb\u003eright\u003c/b\u003e onto \u003cb\u003eR. Varginha\u003c/b\u003e",
                     "maneuver" : "turn-right",
                     "polyline" : {
                        "points" : "dmpxBpndkGuCc@{AY]Ie@I"
                     },
                     "start_location" : {
                        "lat" : -19.9139483,
                        "lng" : -43.9372076
                     },
                     "travel_mode" : "DRIVING"
                  },
                  {
                     "distance" : {
                        "text" : "0.6 km",
                        "value" : 608
                     },
                     "duration" : {
                        "text" : "2 mins",
                        "value" : 95
                     },
                     "end_location" : {
                        "lat" : -19.9127637,
                        "lng" : -43.9310629
                     },
                     "html_instructions" : "Turn \u003cb\u003eright\u003c/b\u003e onto \u003cb\u003eR. Célio de Castro\u003c/b\u003e\u003cdiv style=\"font-size:0.9em\"\u003eDestination will be on the right\u003c/div\u003e",
                     "maneuver" : "turn-right",
                     "polyline" : {
                        "points" : "ncpxB~kdkG?o@?k@?cA?oBGsG?w@?qA?sA@y@@Y@ODWDUD_@Fc@LeAFk@BO@GBE@CBCBEBC@A"
                     },
                     "start_location" : {
                        "lat" : -19.9124036,
                        "lng" : -43.9368048
                     },
                     "travel_mode" : "DRIVING"
                  }
               ],
               "traffic_speed_entry" : [],
               "via_waypoint" : []
            },
            {
               "distance" : {
                  "text" : "2.4 km",
                  "value" : 2444
               },
               "duration" : {
                  "text" : "8 mins",
                  "value" : 483
               },
               "end_address" : "Av. Olegário Maciel, 748 - Centro, Belo Horizonte - MG, 30180-110, Brazil",
               "end_location" : {
                  "lat" : -19.9209476,
                  "lng" : -43.9447298
               },
               "start_address" : "R. Célio de Castro, 869 - Floresta, Belo Horizonte - MG, Brazil",
               "start_location" : {
                  "lat" : -19.9127637,
                  "lng" : -43.9310629
               },
               "steps" : [
                  {
                     "distance" : {
                        "text" : "49 m",
                        "value" : 49
                     },
                     "duration" : {
                        "text" : "1 min",
                        "value" : 9
                     },
                     "end_location" : {
                        "lat" : -19.9131516,
                        "lng" : -43.9308349
                     },
                     "html_instructions" : "Head \u003cb\u003esoutheast\u003c/b\u003e on \u003cb\u003eR. Célio de Castro\u003c/b\u003e toward \u003cb\u003eAv. do Contorno\u003c/b\u003e",
                     "polyline" : {
                        "points" : "vepxBbhckGBALIRKLGHENG"
                     },
                     "start_location" : {
                        "lat" : -19.9127637,
                        "lng" : -43.9310629
                     },
                     "travel_mode" : "DRIVING"
                  },
                  {
                     "distance" : {
                        "text" : "0.1 km",
                        "value" : 101
                     },
                     "duration" : {
                        "text" : "1 min",
                        "value" : 28
                     },
                     "end_location" : {
                        "lat" : -19.9135807,
                        "lng" : -43.9316901
                     },
                     "html_instructions" : "Turn \u003cb\u003eright\u003c/b\u003e onto \u003cb\u003eAv. do Contorno\u003c/b\u003e",
                     "maneuver" : "turn-right",
                     "polyline" : {
                        "points" : "dhpxBtfckGb@bA^bAPb@"
                     },
                     "start_location" : {
                        "lat" : -19.9131516,
                        "lng" : -43.9308349
                     },
                     "travel_mode" : "DRIVING"
                  },
                  {
                     "distance" : {
                        "text" : "0.3 km",
                        "value" : 253
                     },
                     "duration" : {
                        "text" : "1 min",
                        "value" : 41
                     },
                     "end_location" : {
                        "lat" : -19.9148056,
                        "lng" : -43.9337105
                     },
                     "html_instructions" : "Slight \u003cb\u003eleft\u003c/b\u003e to stay on \u003cb\u003eAv. do Contorno\u003c/b\u003e",
                     "maneuver" : "turn-slight-left",
                     "polyline" : {
                        "points" : "zjpxB`lckG\\Rj@pAXj@^p@^p@FP^|@h@lA"
                     },
                     "start_location" : {
                        "lat" : -19.9135807,
                        "lng" : -43.9316901
                     },
                     "travel_mode" : "DRIVING"
                  },
                  {
                     "distance" : {
                        "text" : "0.3 km",
                        "value" : 343
                     },
                     "duration" : {
                        "text" : "1 min",
                        "value" : 58
                     },
                     "end_location" : {
                        "lat" : -19.9141482,
                        "lng" : -43.9368585
                     },
                     "html_instructions" : "Turn \u003cb\u003eright\u003c/b\u003e to stay on \u003cb\u003eAv. do Contorno\u003c/b\u003e",
                     "maneuver" : "turn-right",
                     "polyline" : {
                        "points" : "prpxBtxckGCJALGTIb@ANAD@D?D@B@B@BFDIXIVc@vCa@tCUpBGZ"
                     },
                     "start_location" : {
                        "lat" : -19.9148056,
                        "lng" : -43.9337105
                     },
                     "travel_mode" : "DRIVING"
                  },
                  {
                     "distance" : {
                        "text" : "0.9 km",
                        "value" : 852
                     },
                     "duration" : {
                        "text" : "2 mins",
                        "value" : 90
                     },
                     "end_location" : {
                        "lat" : -19.9139009,
                        "lng" : -43.943704
                     },
                     "html_instructions" : "Slight \u003cb\u003eright\u003c/b\u003e to stay on \u003cb\u003eAv. do Contorno\u003c/b\u003e",
                     "maneuver" : "turn-slight-right",
                     "polyline" : {
                        "points" : "lnpxBjldkGg@dAmGtGQRUTINGRKTCHAFG^A^E^Az@@p@@T@HHf@J^Vp@\\r@~EbKn@dB"
                     },
                     "start_location" : {
                        "lat" : -19.9141482,
                        "lng" : -43.9368585
                     },
                     "travel_mode" : "DRIVING"
                  },
                  {
                     "distance" : {
                        "text" : "0.1 km",
                        "value" : 104
                     },
                     "duration" : {
                        "text" : "1 min",
                        "value" : 39
                     },
                     "end_location" : {
                        "lat" : -19.9145121,
                        "lng" : -43.9430729
                     },
                     "html_instructions" : "Turn \u003cb\u003eleft\u003c/b\u003e onto \u003cb\u003eR. Paulo de Frontin\u003c/b\u003e",
                     "maneuver" : "turn-left",
                     "polyline" : {
                        "points" : "zlpxBbwekGP@F?D?DA@?BADE`@e@LSJWJc@"
                     },
                     "start_location" : {
                        "lat" : -19.9139009,
                        "lng" : -43.943704
                     },
                     "travel_mode" : "DRIVING"
                  },
                  {
                     "distance" : {
                        "text" : "93 m",
                        "value" : 93
                     },
                     "duration" : {
                        "text" : "1 min",
                        "value" : 35
                     },
                     "end_location" : {
                        "lat" : -19.9153129,
                        "lng" : -43.9431282
                     },
                     "html_instructions" : "Turn \u003cb\u003eright\u003c/b\u003e onto \u003cb\u003eAv. Olegário Maciel\u003c/b\u003e",
                     "maneuver" : "turn-right",
                     "polyline" : {
                        "points" : "tppxBdsekGFCDCBAB?@?nBZF?FAFC"
                     },
                     "start_location" : {
                        "lat" : -19.9145121,
                        "lng" : -43.9430729
                     },
                     "travel_mode" : "DRIVING"
                  },
                  {
                     "distance" : {
                        "text" : "0.6 km",
                        "value" : 649
                     },
                     "duration" : {
                        "text" : "3 mins",
                        "value" : 183
                     },
                     "end_location" : {
                        "lat" : -19.9209476,
                        "lng" : -43.9447298
                     },
                     "html_instructions" : "Slight \u003cb\u003eright\u003c/b\u003e to stay on \u003cb\u003eAv. Olegário Maciel\u003c/b\u003e",
                     "maneuver" : "turn-slight-right",
                     "polyline" : {
                        "points" : "tupxBpsekGNBnA\\bDr@pF`AdBXrC`@rFdAbCd@"
                     },
                     "start_location" : {
                        "lat" : -19.9153129,
                        "lng" : -43.9431282
                     },
                     "travel_mode" : "DRIVING"
                  }
               ],
               "traffic_speed_entry" : [],
               "via_waypoint" : []
            },
            {
               "distance" : {
                  "text" : "1.4 km",
                  "value" : 1378
               },
               "duration" : {
                  "text" : "7 mins",
                  "value" : 400
               },
               "end_address" : "Obelisco Praça Sete - Av. Afonso Pena - Centro, Belo Horizonte - MG, 31840-190, Brazil",
               "end_location" : {
                  "lat" : -19.9192293,
                  "lng" : -43.938569
               },
               "start_address" : "Av. Olegário Maciel, 748 - Centro, Belo Horizonte - MG, 30180-110, Brazil",
               "start_location" : {
                  "lat" : -19.9209476,
                  "lng" : -43.9447298
               },
               "steps" : [
                  {
                     "distance" : {
                        "text" : "65 m",
                        "value" : 65
                     },
                     "duration" : {
                        "text" : "1 min",
                        "value" : 19
                     },
                     "end_location" : {
                        "lat" : -19.92151,
                        "lng" : -43.9448928
                     },
                     "html_instructions" : "Head \u003cb\u003esouth\u003c/b\u003e on \u003cb\u003eAv. Olegário Maciel\u003c/b\u003e toward \u003cb\u003eRua dos Goitacazes\u003c/b\u003e",
                     "polyline" : {
                        "points" : "|xqxBp}ekGnB^"
                     },
                     "start_location" : {
                        "lat" : -19.9209476,
                        "lng" : -43.9447298
                     },
                     "travel_mode" : "DRIVING"
                  },
                  {
                     "distance" : {
                        "text" : "0.1 km",
                        "value" : 115
                     },
                     "duration" : {
                        "text" : "1 min",
                        "value" : 49
                     },
                     "end_location" : {
                        "lat" : -19.9212758,
                        "lng" : -43.9459678
                     },
                     "html_instructions" : "Turn \u003cb\u003eright\u003c/b\u003e onto \u003cb\u003eRua dos Goitacazes\u003c/b\u003e",
                     "maneuver" : "turn-right",
                     "polyline" : {
                        "points" : "l|qxBp~ekGOfA]nC"
                     },
                     "start_location" : {
                        "lat" : -19.92151,
                        "lng" : -43.9448928
                     },
                     "travel_mode" : "DRIVING"
                  },
                  {
                     "distance" : {
                        "text" : "0.1 km",
                        "value" : 111
                     },
                     "duration" : {
                        "text" : "1 min",
                        "value" : 41
                     },
                     "end_location" : {
                        "lat" : -19.9220903,
                        "lng" : -43.9456585
                     },
                     "html_instructions" : "Sharp \u003cb\u003eleft\u003c/b\u003e onto \u003cb\u003eAv. Bias Fortes\u003c/b\u003e",
                     "maneuver" : "turn-sharp-left",
                     "polyline" : {
                        "points" : "~zqxBhefkGLXdAk@lAk@"
                     },
                     "start_location" : {
                        "lat" : -19.9212758,
                        "lng" : -43.9459678
                     },
                     "travel_mode" : "DRIVING"
                  },
                  {
                     "distance" : {
                        "text" : "0.1 km",
                        "value" : 130
                     },
                     "duration" : {
                        "text" : "1 min",
                        "value" : 46
                     },
                     "end_location" : {
                        "lat" : -19.9231144,
                        "lng" : -43.9459322
                     },
                     "html_instructions" : "Turn \u003cb\u003eright\u003c/b\u003e onto \u003cb\u003ePraça Raul Soares\u003c/b\u003e",
                     "maneuver" : "turn-right",
                     "polyline" : {
                        "points" : "``rxBjcfkGDFFJHJFHHFRJPDRDJ?L?J?LALALCJEJE"
                     },
                     "start_location" : {
                        "lat" : -19.9220903,
                        "lng" : -43.9456585
                     },
                     "travel_mode" : "DRIVING"
                  },
                  {
                     "distance" : {
                        "text" : "0.2 km",
                        "value" : 233
                     },
                     "duration" : {
                        "text" : "1 min",
                        "value" : 80
                     },
                     "end_location" : {
                        "lat" : -19.9226034,
                        "lng" : -43.9444358
                     },
                     "html_instructions" : "Slight \u003cb\u003eleft\u003c/b\u003e to stay on \u003cb\u003ePraça Raul Soares\u003c/b\u003e (signs for \u003cb\u003ePraça Sete\u003c/b\u003e/\u003cb\u003ePça. Estação\u003c/b\u003e/\u003cb\u003eSerr. S. Pinto\u003c/b\u003e)",
                     "maneuver" : "turn-slight-left",
                     "polyline" : {
                        "points" : "lfrxB`efkGBA@?BA@ABA@ABA@A?I?I@GBIBEDGBGBIBGBIDQ@K@O?MAOAMCMCMGKEKIKGKKGIGMGKEKCGAG?G?G?G?G@G@G@"
                     },
                     "start_location" : {
                        "lat" : -19.9231144,
                        "lng" : -43.9459322
                     },
                     "travel_mode" : "DRIVING"
                  },
                  {
                     "distance" : {
                        "text" : "0.7 km",
                        "value" : 724
                     },
                     "duration" : {
                        "text" : "3 mins",
                        "value" : 165
                     },
                     "end_location" : {
                        "lat" : -19.9192293,
                        "lng" : -43.938569
                     },
                     "html_instructions" : "Turn \u003cb\u003eright\u003c/b\u003e onto \u003cb\u003eAv. Amazonas\u003c/b\u003e\u003cdiv style=\"font-size:0.9em\"\u003eDestination will be on the left\u003c/div\u003e",
                     "maneuver" : "turn-right",
                     "polyline" : {
                        "points" : "fcrxBv{ekGICKECCGEY[MW{@gBM]OYYo@OYISKSGMIUYi@Ui@Wi@CICKu@}AqBkEWa@eC{FKg@IS"
                     },
                     "start_location" : {
                        "lat" : -19.9226034,
                        "lng" : -43.9444358
                     },
                     "travel_mode" : "DRIVING"
                  }
               ],
               "traffic_speed_entry" : [],
               "via_waypoint" : []
            },
            {
               "distance" : {
                  "text" : "0.6 km",
                  "value" : 593
               },
               "duration" : {
                  "text" : "3 mins",
                  "value" : 150
               },
               "end_address" : "Rua Guaicurus, 348-354 - Centro, Belo Horizonte - MG, 30111-060, Brazil",
               "end_location" : {
                  "lat" : -19.9152414,
                  "lng" : -43.9368628
               },
               "start_address" : "Obelisco Praça Sete - Av. Afonso Pena - Centro, Belo Horizonte - MG, 31840-190, Brazil",
               "start_location" : {
                  "lat" : -19.9192293,
                  "lng" : -43.938569
               },
               "steps" : [
                  {
                     "distance" : {
                        "text" : "0.2 km",
                        "value" : 194
                     },
                     "duration" : {
                        "text" : "1 min",
                        "value" : 45
                     },
                     "end_location" : {
                        "lat" : -19.9182807,
                        "lng" : -43.9370151
                     },
                     "html_instructions" : "Head \u003cb\u003enortheast\u003c/b\u003e on \u003cb\u003eAv. Amazonas\u003c/b\u003e toward \u003cb\u003eAv. Afonso Pena\u003c/b\u003e",
                     "polyline" : {
                        "points" : "dnqxB`wdkGISa@g@Ye@_AsBw@_B"
                     },
                     "start_location" : {
                        "lat" : -19.9192293,
                        "lng" : -43.938569
                     },
                     "travel_mode" : "DRIVING"
                  },
                  {
                     "distance" : {
                        "text" : "0.3 km",
                        "value" : 331
                     },
                     "duration" : {
                        "text" : "1 min",
                        "value" : 84
                     },
                     "end_location" : {
                        "lat" : -19.9154002,
                        "lng" : -43.9362362
                     },
                     "html_instructions" : "Turn \u003cb\u003eleft\u003c/b\u003e onto \u003cb\u003eR. Espírito Santo\u003c/b\u003e (signs for \u003cb\u003eAv. Crist. Machado\u003c/b\u003e/\u003cb\u003ePampulha\u003c/b\u003e/\u003cb\u003eAerop. Internacional\u003c/b\u003e/\u003cb\u003eVitória\u003c/b\u003e)",
                     "maneuver" : "turn-left",
                     "polyline" : {
                        "points" : "fhqxBjmdkGWCs@Ou@McCc@mAUcASIAGAkASiAS"
                     },
                     "start_location" : {
                        "lat" : -19.9182807,
                        "lng" : -43.9370151
                     },
                     "travel_mode" : "DRIVING"
                  },
                  {
                     "distance" : {
                        "text" : "68 m",
                        "value" : 68
                     },
                     "duration" : {
                        "text" : "1 min",
                        "value" : 21
                     },
                     "end_location" : {
                        "lat" : -19.9152414,
                        "lng" : -43.9368628
                     },
                     "html_instructions" : "Turn \u003cb\u003eleft\u003c/b\u003e onto \u003cb\u003eRua Guaicurus\u003c/b\u003e\u003cdiv style=\"font-size:0.9em\"\u003eDestination will be on the left\u003c/div\u003e",
                     "maneuver" : "turn-left",
                     "polyline" : {
                        "points" : "fvpxBnhdkG_@zB"
                     },
                     "start_location" : {
                        "lat" : -19.9154002,
                        "lng" : -43.9362362
                     },
                     "travel_mode" : "DRIVING"
                  }
               ],
               "traffic_speed_entry" : [],
               "via_waypoint" : []
            },
            {
               "distance" : {
                  "text" : "1.0 km",
                  "value" : 1033
               },
               "duration" : {
                  "text" : "6 mins",
                  "value" : 337
               },
               "end_address" : "Av. do Contorno, 340 - Santa Efigênia, Belo Horizonte - MG, 30110-017, Brazil",
               "end_location" : {
                  "lat" : -19.9140985,
                  "lng" : -43.9417671
               },
               "start_address" : "Rua Guaicurus, 348-354 - Centro, Belo Horizonte - MG, 30111-060, Brazil",
               "start_location" : {
                  "lat" : -19.9152414,
                  "lng" : -43.9368628
               },
               "steps" : [
                  {
                     "distance" : {
                        "text" : "0.2 km",
                        "value" : 212
                     },
                     "duration" : {
                        "text" : "1 min",
                        "value" : 65
                     },
                     "end_location" : {
                        "lat" : -19.9147549,
                        "lng" : -43.9388253
                     },
                     "html_instructions" : "Head \u003cb\u003ewest\u003c/b\u003e on \u003cb\u003eRua Guaicurus\u003c/b\u003e toward \u003cb\u003eR. Rio de Janeiro\u003c/b\u003e",
                     "polyline" : {
                        "points" : "fupxBjldkGAD_@`C_@~B_@`C"
                     },
                     "start_location" : {
                        "lat" : -19.9152414,
                        "lng" : -43.9368628
                     },
                     "travel_mode" : "DRIVING"
                  },
                  {
                     "distance" : {
                        "text" : "0.3 km",
                        "value" : 276
                     },
                     "duration" : {
                        "text" : "2 mins",
                        "value" : 97
                     },
                     "end_location" : {
                        "lat" : -19.9171591,
                        "lng" : -43.9394812
                     },
                     "html_instructions" : "Turn \u003cb\u003eleft\u003c/b\u003e onto \u003cb\u003eR. São Paulo\u003c/b\u003e",
                     "maneuver" : "turn-left",
                     "polyline" : {
                        "points" : "drpxBtxdkGhAPhAPJBJBfARhARPDr@LpATJB"
                     },
                     "start_location" : {
                        "lat" : -19.9147549,
                        "lng" : -43.9388253
                     },
                     "travel_mode" : "DRIVING"
                  },
                  {
                     "distance" : {
                        "text" : "0.2 km",
                        "value" : 174
                     },
                     "duration" : {
                        "text" : "1 min",
                        "value" : 51
                     },
                     "end_location" : {
                        "lat" : -19.9160326,
                        "lng" : -43.9404529
                     },
                     "html_instructions" : "Turn \u003cb\u003eright\u003c/b\u003e onto \u003cb\u003eAv. Afonso Pena\u003c/b\u003e",
                     "maneuver" : "turn-right",
                     "polyline" : {
                        "points" : "faqxBv|dkGBJ@D@DADAHCHCD]RgCnAw@d@"
                     },
                     "start_location" : {
                        "lat" : -19.9171591,
                        "lng" : -43.9394812
                     },
                     "travel_mode" : "DRIVING"
                  },
                  {
                     "distance" : {
                        "text" : "89 m",
                        "value" : 89
                     },
                     "duration" : {
                        "text" : "1 min",
                        "value" : 20
                     },
                     "end_location" : {
                        "lat" : -19.9152571,
                        "lng" : -43.9403703
                     },
                     "html_instructions" : "\u003cb\u003eAv. Afonso Pena\u003c/b\u003e turns slightly \u003cb\u003eright\u003c/b\u003e and becomes \u003cb\u003ePraça Rio Branco\u003c/b\u003e/\u003cb\u003eR. Curitiba\u003c/b\u003e",
                     "polyline" : {
                        "points" : "dzpxBxbekGMDG@E@C?E?SCWEgAO"
                     },
                     "start_location" : {
                        "lat" : -19.9160326,
                        "lng" : -43.9404529
                     },
                     "travel_mode" : "DRIVING"
                  },
                  {
                     "distance" : {
                        "text" : "64 m",
                        "value" : 64
                     },
                     "duration" : {
                        "text" : "1 min",
                        "value" : 18
                     },
                     "end_location" : {
                        "lat" : -19.9150547,
                        "lng" : -43.9408238
                     },
                     "html_instructions" : "Turn \u003cb\u003eleft\u003c/b\u003e onto \u003cb\u003eCorredor MOVE Centro\u003c/b\u003e/\u003cb\u003ePraça Rio Branco\u003c/b\u003e",
                     "maneuver" : "turn-left",
                     "polyline" : {
                        "points" : "jupxBhbekGKAMAGn@Gl@"
                     },
                     "start_location" : {
                        "lat" : -19.9152571,
                        "lng" : -43.9403703
                     },
                     "travel_mode" : "DRIVING"
                  },
                  {
                     "distance" : {
                        "text" : "0.1 km",
                        "value" : 96
                     },
                     "duration" : {
                        "text" : "1 min",
                        "value" : 40
                     },
                     "end_location" : {
                        "lat" : -19.9143135,
                        "lng" : -43.9409559
                     },
                     "html_instructions" : "\u003cb\u003eCorredor MOVE Centro\u003c/b\u003e/\u003cb\u003ePraça Rio Branco\u003c/b\u003e turns slightly \u003cb\u003eright\u003c/b\u003e and becomes \u003cb\u003eR. Saturnino de Brito\u003c/b\u003e",
                     "polyline" : {
                        "points" : "`tpxBbeekGCFELADCDABC@C@E@UB}AS"
                     },
                     "start_location" : {
                        "lat" : -19.9150547,
                        "lng" : -43.9408238
                     },
                     "travel_mode" : "DRIVING"
                  },
                  {
                     "distance" : {
                        "text" : "0.1 km",
                        "value" : 122
                     },
                     "duration" : {
                        "text" : "1 min",
                        "value" : 46
                     },
                     "end_location" : {
                        "lat" : -19.9140985,
                        "lng" : -43.9417671
                     },
                     "html_instructions" : "Turn \u003cb\u003eleft\u003c/b\u003e\u003cdiv style=\"font-size:0.9em\"\u003eDestination will be on the right\u003c/div\u003e",
                     "maneuver" : "turn-left",
                     "polyline" : {
                        "points" : "lopxB~eekGIFGFOHw@`@CB?@?@?@?@@Bp@tA"
                     },
                     "start_location" : {
                        "lat" : -19.9143135,
                        "lng" : -43.9409559
                     },
                     "travel_mode" : "DRIVING"
                  }
               ],
               "traffic_speed_entry" : [],
               "via_waypoint" : []
            }
         ],
         "overview_polyline" : {
            "points" : "bnpxB`kekGp@pALAv@a@HAzBXTFVHDW`@_Cb@gD\\EfCsAxCaBdAi@`Am@dCcAr@_@b@Y|FcD^Wv@RnBf@l@Jf@iEEICEYYOJYHaAh@}A~@aAh@kDo@qHqA}McCcDi@wAW\\gC\\gCJ]J_@NSRUVCdBXrDn@xAZzH~AvB`@d@?x@Ad@In@WZOpBeAb@]Xa@tB_Fv@mBR_AHa@Bq@Am@KkAGu@kBcHu@gCIe@NSb@YjBeAtAw@d@_@rBeATTLFf@FrAJj@FL\\j@nAP`@n@tATd@IDIIIGGCOEWCa@FOD_@w@^v@JC^v@h@jAKZGZ@Nz@xBBHPAtBcAPGIWMYk@sAYo@kA_CuA_Da@}@qAGeAKWEIE_@WOIOJOH]RUHo@b@uCbBsDrBcI`EcBv@eDbBkFtCoGfDqAUqCk@o@IQEE@ULIJj@pAx@|Af@bAfBdE\\XVCxCf@bHpAW~A@VJL|E`Ad@aDgGqAcCe@aEs@yAS_@@e@F_@l@Sx@m@nDw@fGGZg@dAqF}@cAS?{A?sDGkI?eDBsAR}A`@eDJULMx@c@NGb@bAp@fB\\Rj@pAx@|Af@bAhAjCWrAA`@LPSp@eAlH]lCg@dAmGtGg@h@Qb@O^If@G~@?lBB^TfAt@dB~EbKn@dBX@JADAf@k@Xk@Jc@FCHED?vBZNE~A`@bDr@pF`AxFz@vJjBnB^OfA]nCLXrCwALRPT\\Rd@JX?t@Gh@UDC?SDQHMNc@F]@]C]G[MWQWUOYMc@E_@BQAOIa@a@iA_CgAaCsBsEy@iBiCmFeC{FKg@Sg@a@g@Ye@wBsEeGeAcDm@uCg@a@`C_A`G_@`ChAPtATrAV`F|@JBBJBJCNGNeDbBw@d@MDMBI?_C[MAGn@Gl@CFGREHc@H}ASIFWP{@f@?Dr@xA"
         },
         "summary" : "Av. Afonso Pena",
         "warnings" : [],
         "waypoint_order" : [ 0, 1, 2, 3, 4, 5, 6, 7 ]
      }
   ],
   "status" : "OK"
}
