{
   "geocoded_waypoints" : [
      {
         "geocoder_status" : "OK",
         "place_id" : "ChIJR8XdnMSZpgARmu_lSytI0zY",
         "types" : [ "street_address" ]
      },
      {
         "geocoder_status" : "OK",
         "place_id" : "ChIJX15RIvePpgARLKQNmvg0Z8M",
         "types" : [ "premise" ]
      }
   ],
   "routes" : [
      {
         "bounds" : {
            "northeast" : {
               "lat" : -19.821654,
               "lng" : -43.9272417
            },
            "southwest" : {
               "lat" : -19.9366622,
               "lng" : -43.9467585
            }
         },
         "copyrights" : "Map data ©2017 Google",
         "legs" : [
            {
               "distance" : {
                  "text" : "14.9 km",
                  "value" : 14861
               },
               "duration" : {
                  "text" : "26 mins",
                  "value" : 1559
               },
               "end_address" : "Av. Cristiano Machado, 11833 - Vila Cloris, Belo Horizonte - MG, Brazil",
               "end_location" : {
                  "lat" : -19.821654,
                  "lng" : -43.9467585
               },
               "start_address" : "R. Rio Grande do Norte, 1204 - Funcionários, Belo Horizonte - MG, 30130-131, Brazil",
               "start_location" : {
                  "lat" : -19.9362369,
                  "lng" : -43.9322733
               },
               "steps" : [
                  {
                     "distance" : {
                        "text" : "35 m",
                        "value" : 35
                     },
                     "duration" : {
                        "text" : "1 min",
                        "value" : 13
                     },
                     "end_location" : {
                        "lat" : -19.9363491,
                        "lng" : -43.9321855
                     },
                     "html_instructions" : "Head \u003cb\u003esouth\u003c/b\u003e on \u003cb\u003eAv. Getúlio Vargas\u003c/b\u003e toward \u003cb\u003eAv. Getúlio Vargas\u003c/b\u003e",
                     "polyline" : {
                        "points" : "nxtxBtockGb@FGKEK"
                     },
                     "start_location" : {
                        "lat" : -19.9362369,
                        "lng" : -43.9322733
                     },
                     "travel_mode" : "DRIVING"
                  },
                  {
                     "distance" : {
                        "text" : "0.1 km",
                        "value" : 128
                     },
                     "duration" : {
                        "text" : "1 min",
                        "value" : 30
                     },
                     "end_location" : {
                        "lat" : -19.9366622,
                        "lng" : -43.93100769999999
                     },
                     "html_instructions" : "Turn \u003cb\u003eright\u003c/b\u003e onto \u003cb\u003eRua dos Inconfidentes\u003c/b\u003e",
                     "maneuver" : "turn-right",
                     "polyline" : {
                        "points" : "dytxBdockGZiBZgBBM@K"
                     },
                     "start_location" : {
                        "lat" : -19.9363491,
                        "lng" : -43.9321855
                     },
                     "travel_mode" : "DRIVING"
                  },
                  {
                     "distance" : {
                        "text" : "0.4 km",
                        "value" : 404
                     },
                     "duration" : {
                        "text" : "1 min",
                        "value" : 86
                     },
                     "end_location" : {
                        "lat" : -19.9331478,
                        "lng" : -43.9300133
                     },
                     "html_instructions" : "Turn \u003cb\u003eleft\u003c/b\u003e at the 1st cross street onto \u003cb\u003eRua Professor Moraes\u003c/b\u003e",
                     "maneuver" : "turn-left",
                     "polyline" : {
                        "points" : "b{txBxgckGiB]GAqB_@g@KaAQ{Ba@]GUEqCg@m@Q"
                     },
                     "start_location" : {
                        "lat" : -19.9366622,
                        "lng" : -43.93100769999999
                     },
                     "travel_mode" : "DRIVING"
                  },
                  {
                     "distance" : {
                        "text" : "1.6 km",
                        "value" : 1623
                     },
                     "duration" : {
                        "text" : "5 mins",
                        "value" : 304
                     },
                     "end_location" : {
                        "lat" : -19.9205475,
                        "lng" : -43.9376498
                     },
                     "html_instructions" : "Turn \u003cb\u003eleft\u003c/b\u003e onto \u003cb\u003eAv. Afonso Pena\u003c/b\u003e",
                     "maneuver" : "turn-left",
                     "polyline" : {
                        "points" : "detxBpackGWGWGQHOHgE`Cq@Za@TaCnAoBdAOHEBGDGDSJa@P}BjAgB`ASJk@ZcDhBULgAh@KDIFIDm@\\mKlFIFIDYPgKxFSLYNg@VOJYHaAh@{@d@a@Xe@X[N"
                     },
                     "start_location" : {
                        "lat" : -19.9331478,
                        "lng" : -43.9300133
                     },
                     "travel_mode" : "DRIVING"
                  },
                  {
                     "distance" : {
                        "text" : "0.7 km",
                        "value" : 693
                     },
                     "duration" : {
                        "text" : "3 mins",
                        "value" : 164
                     },
                     "end_location" : {
                        "lat" : -19.914509,
                        "lng" : -43.9360148
                     },
                     "html_instructions" : "Turn \u003cb\u003eright\u003c/b\u003e onto \u003cb\u003eR. Espírito Santo\u003c/b\u003e (signs for \u003cb\u003eAv. Crist. Machado\u003c/b\u003e/\u003cb\u003ePampulha\u003c/b\u003e/\u003cb\u003eAerop. Internacional\u003c/b\u003e/\u003cb\u003eVitória\u003c/b\u003e)",
                     "maneuver" : "turn-right",
                     "polyline" : {
                        "points" : "lvqxBhqdkGa@GiCg@o@KiCe@_B[WCs@Ou@McCc@mAUcASIAGAkASiASyAUwAW"
                     },
                     "start_location" : {
                        "lat" : -19.9205475,
                        "lng" : -43.9376498
                     },
                     "travel_mode" : "DRIVING"
                  },
                  {
                     "distance" : {
                        "text" : "0.1 km",
                        "value" : 104
                     },
                     "duration" : {
                        "text" : "1 min",
                        "value" : 15
                     },
                     "end_location" : {
                        "lat" : -19.9141482,
                        "lng" : -43.9368585
                     },
                     "html_instructions" : "Turn \u003cb\u003eleft\u003c/b\u003e onto \u003cb\u003eAv. do Contorno\u003c/b\u003e",
                     "maneuver" : "turn-left",
                     "polyline" : {
                        "points" : "tppxB`gdkGi@ZUpBGZ"
                     },
                     "start_location" : {
                        "lat" : -19.914509,
                        "lng" : -43.9360148
                     },
                     "travel_mode" : "DRIVING"
                  },
                  {
                     "distance" : {
                        "text" : "19 m",
                        "value" : 19
                     },
                     "duration" : {
                        "text" : "1 min",
                        "value" : 2
                     },
                     "end_location" : {
                        "lat" : -19.914109,
                        "lng" : -43.9370331
                     },
                     "html_instructions" : "Keep \u003cb\u003eleft\u003c/b\u003e to continue on \u003cb\u003eR. Vinte Um de Abril\u003c/b\u003e",
                     "maneuver" : "keep-left",
                     "polyline" : {
                        "points" : "lnpxBjldkGAJAJCH"
                     },
                     "start_location" : {
                        "lat" : -19.9141482,
                        "lng" : -43.9368585
                     },
                     "travel_mode" : "DRIVING"
                  },
                  {
                     "distance" : {
                        "text" : "0.3 km",
                        "value" : 276
                     },
                     "duration" : {
                        "text" : "1 min",
                        "value" : 21
                     },
                     "end_location" : {
                        "lat" : -19.9124394,
                        "lng" : -43.9389695
                     },
                     "html_instructions" : "Keep \u003cb\u003eright\u003c/b\u003e to stay on \u003cb\u003eR. Vinte Um de Abril\u003c/b\u003e",
                     "maneuver" : "keep-right",
                     "polyline" : {
                        "points" : "dnpxBlmdkGCHABGLIRMTWZ[^wA|AuAvAeAjA"
                     },
                     "start_location" : {
                        "lat" : -19.914109,
                        "lng" : -43.9370331
                     },
                     "travel_mode" : "DRIVING"
                  },
                  {
                     "distance" : {
                        "text" : "0.2 km",
                        "value" : 211
                     },
                     "duration" : {
                        "text" : "1 min",
                        "value" : 16
                     },
                     "end_location" : {
                        "lat" : -19.9107334,
                        "lng" : -43.9387148
                     },
                     "html_instructions" : "Take the ramp to \u003cb\u003eAv. C. Machado\u003c/b\u003e/\u003cb\u003eAerop. Intern.\u003c/b\u003e/\u003cb\u003eVitória\u003c/b\u003e",
                     "polyline" : {
                        "points" : "vcpxBpydkGYJA@]LQHKDOBS@E?S?WAGAYEUGSIWMYSMO[W"
                     },
                     "start_location" : {
                        "lat" : -19.9124394,
                        "lng" : -43.9389695
                     },
                     "travel_mode" : "DRIVING"
                  },
                  {
                     "distance" : {
                        "text" : "0.5 km",
                        "value" : 494
                     },
                     "duration" : {
                        "text" : "1 min",
                        "value" : 27
                     },
                     "end_location" : {
                        "lat" : -19.9066111,
                        "lng" : -43.9375807
                     },
                     "html_instructions" : "Merge onto \u003cb\u003eTúnel Pres. Tancredo Neves\u003c/b\u003e",
                     "maneuver" : "merge",
                     "polyline" : {
                        "points" : "`yoxB|wdkGY[Y]QS[YsAq@WKa@OMEOCQEQCg@Gw@IgAE]CK?K?O@Q?U@U@}@BQ?Y@K?O?E@G?KAUCc@C"
                     },
                     "start_location" : {
                        "lat" : -19.9107334,
                        "lng" : -43.9387148
                     },
                     "travel_mode" : "DRIVING"
                  },
                  {
                     "distance" : {
                        "text" : "1.8 km",
                        "value" : 1846
                     },
                     "duration" : {
                        "text" : "2 mins",
                        "value" : 124
                     },
                     "end_location" : {
                        "lat" : -19.8955887,
                        "lng" : -43.9272466
                     },
                     "html_instructions" : "Continue onto \u003cb\u003eAv. Cristiano Machado\u003c/b\u003e",
                     "polyline" : {
                        "points" : "h_oxBzpdkGWCUEa@MUIWOSMm@i@SSa@k@a@{@K]KYKc@c@aB?AKg@U{@EM{@sD_AsDUcAEKKc@ACMe@UiAWkAEUCUAGESAEEUMg@Kg@S_AOm@CKCKU}@AIOi@Sc@MWKQY]OQIGOMWQSKMGUKOG[K_@GUE]GGA}@KWASCE?iBQcBQ}@KmAM{AO_D]kFe@eAKgBO"
                     },
                     "start_location" : {
                        "lat" : -19.9066111,
                        "lng" : -43.9375807
                     },
                     "travel_mode" : "DRIVING"
                  },
                  {
                     "distance" : {
                        "text" : "3.1 km",
                        "value" : 3097
                     },
                     "duration" : {
                        "text" : "5 mins",
                        "value" : 274
                     },
                     "end_location" : {
                        "lat" : -19.8685563,
                        "lng" : -43.9281008
                     },
                     "html_instructions" : "Keep \u003cb\u003eleft\u003c/b\u003e to stay on \u003cb\u003eAv. Cristiano Machado\u003c/b\u003e",
                     "maneuver" : "keep-left",
                     "polyline" : {
                        "points" : "lzlxBhpbkGs@A{@ByALeBl@gCn@yAZyAZ_GjAsAXu@P}@NyA\\{Cl@o@HgADc@?]?gDIO?y@@i@?[AgA?w@Aw@AU@W?OBg@Di@Hs@Jq@NiAXy@Ta@La@J[H]H_@Hc@F_@Dk@DY@a@AeAE_@Ea@GoASuA[[I_BYkFeAwAYkAUYEu@Qa@GwBc@wA]aAUgAUwDy@kBYwB_@w@OsASkAOq@CMAO@W?g@@m@@o@He@Fk@F_Bd@_Bf@E@C?A@A?A@QBs@Ps@JeABe@@UA"
                     },
                     "start_location" : {
                        "lat" : -19.8955887,
                        "lng" : -43.9272466
                     },
                     "travel_mode" : "DRIVING"
                  },
                  {
                     "distance" : {
                        "text" : "0.2 km",
                        "value" : 171
                     },
                     "duration" : {
                        "text" : "1 min",
                        "value" : 12
                     },
                     "end_location" : {
                        "lat" : -19.8672039,
                        "lng" : -43.9288654
                     },
                     "html_instructions" : "Take the ramp on the \u003cb\u003eleft\u003c/b\u003e to \u003cb\u003eVenda Nova\u003c/b\u003e/\u003cb\u003eAerop. Internacional\u003c/b\u003e/\u003cb\u003eLagoa Santa\u003c/b\u003e/\u003cb\u003eSão Bernardo\u003c/b\u003e",
                     "polyline" : {
                        "points" : "nqgxBrubkGm@N]LwB`Ac@Zg@\\"
                     },
                     "start_location" : {
                        "lat" : -19.8685563,
                        "lng" : -43.9281008
                     },
                     "travel_mode" : "DRIVING"
                  },
                  {
                     "distance" : {
                        "text" : "85 m",
                        "value" : 85
                     },
                     "duration" : {
                        "text" : "1 min",
                        "value" : 6
                     },
                     "end_location" : {
                        "lat" : -19.8665867,
                        "lng" : -43.92935079999999
                     },
                     "html_instructions" : "Keep \u003cb\u003eleft\u003c/b\u003e to continue toward \u003cb\u003eAv. Cristiano Machado\u003c/b\u003e",
                     "maneuver" : "keep-left",
                     "polyline" : {
                        "points" : "~hgxBlzbkGq@h@gAt@"
                     },
                     "start_location" : {
                        "lat" : -19.8672039,
                        "lng" : -43.9288654
                     },
                     "travel_mode" : "DRIVING"
                  },
                  {
                     "distance" : {
                        "text" : "5.0 km",
                        "value" : 4988
                     },
                     "duration" : {
                        "text" : "7 mins",
                        "value" : 422
                     },
                     "end_location" : {
                        "lat" : -19.8265573,
                        "lng" : -43.9431333
                     },
                     "html_instructions" : "Continue onto \u003cb\u003eAv. Cristiano Machado\u003c/b\u003e",
                     "polyline" : {
                        "points" : "degxBl}bkGmBtAWPOJw@p@uBzAwA`AeBnAGBiAz@_Al@MJKDULg@Xs@\\iA^uA`@{@TkC`Am@R[LSFg@Tg@Ry@VWH_@JeBf@MDu@XeATu@Ts@VYHYHq@Pq@PiANcANE@e@F[DmAL[Bg@@_@?]?c@?m@Ce@Cs@G}@Me@G}@Q[Iu@SOEk@SgAc@yBeAu@_@yCuAm@YmAe@]M]MC?e@OcAWs@Kw@MWCSCCAk@GaAEi@ASAo@@u@?kAB{@D_@Ba@D]D}@Ni@Ly@RYFg@PWHa@NSJm@V]LQJs@^IFg@Xs@h@ULaAp@SNYT}@v@i@d@a@XGFe@ZA@eAl@_Ad@}@d@a@TeAl@[PuA~@YTw@|@[`@Y\\Y`@}A`C_ArAc@r@c@n@STYZe@\\[R]RYJ_@Ne@JYFg@Dg@Ds@Fm@DK@[Bs@Du@FqCR}@FaBNi@Hg@H]Fm@NUFsA`@YJcEzA_FhBg@PWJiDrAsBp@i@Tk@To@TQHQD"
                     },
                     "start_location" : {
                        "lat" : -19.8665867,
                        "lng" : -43.92935079999999
                     },
                     "travel_mode" : "DRIVING"
                  },
                  {
                     "distance" : {
                        "text" : "0.7 km",
                        "value" : 687
                     },
                     "duration" : {
                        "text" : "1 min",
                        "value" : 43
                     },
                     "end_location" : {
                        "lat" : -19.821654,
                        "lng" : -43.9467585
                     },
                     "html_instructions" : "Slight \u003cb\u003eleft\u003c/b\u003e onto \u003cb\u003eAv. Vilarinho\u003c/b\u003e\u003cdiv style=\"font-size:0.9em\"\u003eDestination will be on the left\u003c/div\u003e",
                     "maneuver" : "turn-slight-left",
                     "polyline" : {
                        "points" : "~j_xBpsekGGJCBC@EBKB_@LYJWJwAh@sBz@iDnACBcDlA]N]PYPYV_@\\_@`@SVe@r@EDS^OXMZOf@Qp@"
                     },
                     "start_location" : {
                        "lat" : -19.8265573,
                        "lng" : -43.9431333
                     },
                     "travel_mode" : "DRIVING"
                  }
               ],
               "traffic_speed_entry" : [],
               "via_waypoint" : []
            }
         ],
         "overview_polyline" : {
            "points" : "nxtxBtockGb@FGKEKZiB^uB@KiB]yBa@iB]aIwAeAYWGQHwEjCsAp@gGbDeAh@eHtDyDvBsAn@SL{LjGuLxGeB`AYHaAh@}A~@aAh@kDo@qHqA}McCcDi@wAWi@Z]lCCVQd@Wh@s@z@mDtDeAjAYJ_@N]Nc@DY?_@Co@Mk@Wg@c@u@s@k@q@[YsAq@y@[aAS_BQeBIy@@wDJmAIm@Iw@Wk@]aA}@a@k@a@{@Ww@{@oDwCqLi@wBaAqEm@}Ck@eCWgAc@mAYi@i@o@YUk@]oAg@{AWiMoAmP_BgBOs@A{@ByALeBl@gCn@sDv@sIdBsB`@uFjAo@HgADaA?wDIgE?}CAuC^{Bh@{Ab@{Bh@cALeAFgBGaAMaHsAcI_BeB[gH{AiCk@wDy@kBYoDo@_Dc@gBCuABuAPk@F_Bd@eBh@IBeATs@JeAB{@?kA\\wB`Ac@ZyAfA}EhDmDlC}DpC_DxBa@R{Av@_D`AgEvA}Ah@oAh@qA`@iErA{Bj@mA`@kAZq@PiANiAPaALiBPgA@aA?sAGqBUcBYmCw@aEiBoEuB{B_A{@[i@OwBc@gBWmBM}@CeB@gCHaAH{ATeDz@y@XaAb@mB`AsDbCuCbCqA~@eFnCaB~@oBtAsA~As@~@eFxHm@p@aAp@w@^eAZaAL{ALiCPgJr@qARkAViBh@}EfBiMzE}CfA{Aj@c@NKNu@V}F|BoJpDw@b@y@t@s@x@k@x@c@x@]bAQp@"
         },
         "summary" : "Av. Cristiano Machado",
         "warnings" : [],
         "waypoint_order" : []
      }
   ],
   "status" : "OK"
}
